Workbook

Sheet Schedule
B1: Date Asset Purchased | C1: FIXED ASSETS | E1: =E57+E110 -> 0 | F1: =F57+F110 -> 0 | G1: =G57+G110 -> 0 | H1: Deprn Rate % | I1: =I57+I110 -> 0 | J1: =J57+J110 -> 0 | K1: =K57+K110 -> 0 | M1: Enter % Personal use of vehicles | O1: =O57+O110 -> 0 | P1: Annual Invest Allow | Q1: =Q57+Q110 -> 0 | R1: =R57+R110 -> 0 | S1: =S57+S110 -> 0 | U1: Date Asset Sold | V1: =V57+V110 -> 0 | W1: =W57+W110 -> 0 | X1: =X57+X110 -> 0 | Y1: =Y57+Y110 -> 0 | Z1: =Z57+Z110 -> 0
C2: Asset Description | D2: Purchase Reference | E2: Original Cost | F2: Accumulated Depreciation | G2: Written Down Book Value | I2: Depreciation Charge current year | J2: Accumulated Depreciation | K2: Written Down Book Value | O2: Written Down Tax Value | Q2: First Year Allowance | R2: W Down Allowance | S2: Written Down Tax Value | V2: Sales Value Assets Sold | W2: Original Cost Assets Sold | X2: Accumulated Depreciation Assets Sold | Y2: Capital Allowance | Z2: Balancing Charge
F4: =[1]Admin!$B$4 -> 45388 | G4: =[1]Admin!$B$4 -> 45388 | J4: =[1]Admin!$B$17 -> 45752 | K4: =[1]Admin!$B$17 -> 45752 | O4: =[1]Admin!$B$4 -> 45388 | P4: =[1]Admin!$G$4 -> 1 | R4: =[1]Admin!$G$5 -> 0.18 | S4: =[1]Admin!$B$17 -> 45752
B6: EXISTING FIXED ASSETS at | D6: =[1]Admin!$B$4 -> 45388
B7: Land & Property | H7: =[1]Admin!$G$13 -> 0
G8: =IF(E8>0,E8-F8," ") | H8: =H$7 -> 0 | I8: =IF(E8>0,MIN(E8*H8,G8)," ") | J8: =IF(E8>0,F8+I8," ") | K8: =IF(E8>0,E8-J8," ") | W8: =IF(V8>0,E8," ") | X8: =IF(V8>0,J8," ")
G9: =IF(E9>0,E9-F9," ") | H9: =H$7 -> 0 | I9: =IF(E9>0,MIN(E9*H9,G9)," ") | J9: =IF(E9>0,F9+I9," ") | K9: =IF(E9>0,E9-J9," ") | W9: =IF(V9>0,E9," ") | X9: =IF(V9>0,J9," ")
G10: =IF(E10>0,E10-F10," ") | H10: =H$7 -> 0 | I10: =IF(E10>0,MIN(E10*H10,G10)," ") | J10: =IF(E10>0,F10+I10," ") | K10: =IF(E10>0,E10-J10," ") | W10: =IF(V10>0,E10," ") | X10: =IF(V10>0,J10," ")
B11: Existing Land & Property | E11: =SUM(E8:E10) -> 0 | F11: =SUM(F8:F10) -> 0 | G11: =SUM(G8:G10) -> 0 | I11: =SUM(I8:I10) -> 0 | J11: =SUM(J8:J10) -> 0 | K11: =SUM(K8:K10) -> 0 | O11: =SUM(O8:O10) -> 0 | Q11: =SUM(Q8:Q10) -> 0 | R11: =SUM(R8:R10) -> 0 | S11: =SUM(S8:S10) -> 0 | V11: =SUM(V8:V10) -> 0 | W11: =SUM(W8:W10) -> 0 | X11: =SUM(X8:X10) -> 0 | Y11: =SUM(Y8:Y10) -> 0 | Z11: =SUM(Z8:Z10) -> 0
B13: Plant & Machinery | H13: =[1]Admin!$G$14 -> 0.1
G14: =IF(E14>0,E14-F14," ") | H14: =H$13 -> 0.1 | I14: =IF(E14>0,MIN(E14*H14,G14)," ") | J14: =IF(E14>0,F14+I14," ") | K14: =IF(E14>0,E14-J14," ") | R14: =IF(O14>0,O14*R$4," ") | S14: =IF(O14>0,O14-R14," ") | W14: =IF(V14>0,E14," ") | X14: =IF(V14>0,J14," ") | Y14: =IF((U14+V14)>0,IF(V14<S14,S14-V14," ")," ") | Z14: =IF((U14+V14)>0,IF(V14>S14,V14-S14," ")," ")
G15: =IF(E15>0,E15-F15," ") | H15: =H$13 -> 0.1 | I15: =IF(E15>0,MIN(E15*H15,G15)," ") | J15: =IF(E15>0,F15+I15," ") | K15: =IF(E15>0,E15-J15," ") | R15: =IF(O15>0,O15*R$4," ") | S15: =IF(O15>0,O15-R15," ") | W15: =IF(V15>0,E15," ") | X15: =IF(V15>0,J15," ") | Y15: =IF((U15+V15)>0,IF(V15<S15,S15-V15," ")," ") | Z15: =IF((U15+V15)>0,IF(V15>S15,V15-S15," ")," ")
G16: =IF(E16>0,E16-F16," ") | H16: =H$13 -> 0.1 | I16: =IF(E16>0,MIN(E16*H16,G16)," ") | J16: =IF(E16>0,F16+I16," ") | K16: =IF(E16>0,E16-J16," ") | R16: =IF(O16>0,O16*R$4," ") | S16: =IF(O16>0,O16-R16," ") | W16: =IF(V16>0,E16," ") | X16: =IF(V16>0,J16," ") | Y16: =IF((U16+V16)>0,IF(V16<S16,S16-V16," ")," ") | Z16: =IF((U16+V16)>0,IF(V16>S16,V16-S16," ")," ")
G17: =IF(E17>0,E17-F17," ") | H17: =H$13 -> 0.1 | I17: =IF(E17>0,MIN(E17*H17,G17)," ") | J17: =IF(E17>0,F17+I17," ") | K17: =IF(E17>0,E17-J17," ") | R17: =IF(O17>0,O17*R$4," ") | S17: =IF(O17>0,O17-R17," ") | W17: =IF(V17>0,E17," ") | X17: =IF(V17>0,J17," ") | Y17: =IF((U17+V17)>0,IF(V17<S17,S17-V17," ")," ") | Z17: =IF((U17+V17)>0,IF(V17>S17,V17-S17," ")," ")
G18: =IF(E18>0,E18-F18," ") | H18: =H$13 -> 0.1 | I18: =IF(E18>0,MIN(E18*H18,G18)," ") | J18: =IF(E18>0,F18+I18," ") | K18: =IF(E18>0,E18-J18," ") | R18: =IF(O18>0,O18*R$4," ") | S18: =IF(O18>0,O18-R18," ") | W18: =IF(V18>0,E18," ") | X18: =IF(V18>0,J18," ") | Y18: =IF((U18+V18)>0,IF(V18<S18,S18-V18," ")," ") | Z18: =IF((U18+V18)>0,IF(V18>S18,V18-S18," ")," ")
B19: Existing Plant & Machinery | E19: =SUM(E14:E18) -> 0 | F19: =SUM(F14:F18) -> 0 | G19: =SUM(G14:G18) -> 0 | I19: =SUM(I14:I18) -> 0 | J19: =SUM(J14:J18) -> 0 | K19: =SUM(K14:K18) -> 0 | O19: =SUM(O14:O18) -> 0 | Q19: =SUM(Q14:Q18) -> 0 | R19: =SUM(R14:R18) -> 0 | S19: =SUM(S14:S18) -> 0 | V19: =SUM(V14:V18) -> 0 | W19: =SUM(W14:W18) -> 0 | X19: =SUM(X14:X18) -> 0 | Y19: =SUM(Y14:Y18) -> 0 | Z19: =SUM(Z14:Z18) -> 0
B21: Fixtures & Fittings | H21: =[1]Admin!$G$15 -> 0.2
G22: =IF(E22>0,E22-F22," ") | H22: =H$21 -> 0.2 | I22: =IF(E22>0,MIN(E22*H22,G22)," ") | J22: =IF(E22>0,F22+I22," ") | K22: =IF(E22>0,E22-J22," ") | R22: =IF(O22>0,O22*R$4," ") | S22: =IF(O22>0,O22-R22," ") | W22: =IF(V22>0,E22," ") | X22: =IF(V22>0,J22," ") | Y22: =IF((U22+V22)>0,IF(V22<S22,S22-V22," ")," ") | Z22: =IF((U22+V22)>0,IF(V22>S22,V22-S22," ")," ")
G23: =IF(E23>0,E23-F23," ") | H23: =H$21 -> 0.2 | I23: =IF(E23>0,MIN(E23*H23,G23)," ") | J23: =IF(E23>0,F23+I23," ") | K23: =IF(E23>0,E23-J23," ") | R23: =IF(O23>0,O23*R$4," ") | S23: =IF(O23>0,O23-R23," ") | W23: =IF(V23>0,E23," ") | X23: =IF(V23>0,J23," ") | Y23: =IF((U23+V23)>0,IF(V23<S23,S23-V23," ")," ") | Z23: =IF((U23+V23)>0,IF(V23>S23,V23-S23," ")," ")
G24: =IF(E24>0,E24-F24," ") | H24: =H$21 -> 0.2 | I24: =IF(E24>0,MIN(E24*H24,G24)," ") | J24: =IF(E24>0,F24+I24," ") | K24: =IF(E24>0,E24-J24," ") | R24: =IF(O24>0,O24*R$4," ") | S24: =IF(O24>0,O24-R24," ") | W24: =IF(V24>0,E24," ") | X24: =IF(V24>0,J24," ") | Y24: =IF((U24+V24)>0,IF(V24<S24,S24-V24," ")," ") | Z24: =IF((U24+V24)>0,IF(V24>S24,V24-S24," ")," ")
G25: =IF(E25>0,E25-F25," ") | H25: =H$21 -> 0.2 | I25: =IF(E25>0,MIN(E25*H25,G25)," ") | J25: =IF(E25>0,F25+I25," ") | K25: =IF(E25>0,E25-J25," ") | R25: =IF(O25>0,O25*R$4," ") | S25: =IF(O25>0,O25-R25," ") | W25: =IF(V25>0,E25," ") | X25: =IF(V25>0,J25," ") | Y25: =IF((U25+V25)>0,IF(V25<S25,S25-V25," ")," ") | Z25: =IF((U25+V25)>0,IF(V25>S25,V25-S25," ")," ")
G26: =IF(E26>0,E26-F26," ") | H26: =H$21 -> 0.2 | I26: =IF(E26>0,MIN(E26*H26,G26)," ") | J26: =IF(E26>0,F26+I26," ") | K26: =IF(E26>0,E26-J26," ") | R26: =IF(O26>0,O26*R$4," ") | S26: =IF(O26>0,O26-R26," ") | W26: =IF(V26>0,E26," ") | X26: =IF(V26>0,J26," ") | Y26: =IF((U26+V26)>0,IF(V26<S26,S26-V26," ")," ") | Z26: =IF((U26+V26)>0,IF(V26>S26,V26-S26," ")," ")
B27: Existing Fixtures & Fittings | E27: =SUM(E22:E26) -> 0 | F27: =SUM(F22:F26) -> 0 | G27: =SUM(G22:G26) -> 0 | I27: =SUM(I22:I26) -> 0 | J27: =SUM(J22:J26) -> 0 | K27: =SUM(K22:K26) -> 0 | O27: =SUM(O22:O26) -> 0 | Q27: =SUM(Q22:Q26) -> 0 | R27: =SUM(R22:R26) -> 0 | S27: =SUM(S22:S26) -> 0 | V27: =SUM(V22:V26) -> 0 | W27: =SUM(W22:W26) -> 0 | X27: =SUM(X22:X26) -> 0 | Y27: =SUM(Y22:Y26) -> 0 | Z27: =SUM(Z22:Z26) -> 0
B29: Computers | H29: =[1]Admin!$G$16 -> 0.33
G30: =IF(E30>0,E30-F30," ") | H30: =H$29 -> 0.33 | I30: =IF(E30>0,MIN(E30*H30,G30)," ") | J30: =IF(E30>0,F30+I30," ") | K30: =IF(E30>0,E30-J30," ") | R30: =IF(O30>0,O30*R$4," ") | S30: =IF(O30>0,O30-R30," ") | W30: =IF(V30>0,E30," ") | X30: =IF(V30>0,J30," ") | Y30: =IF((U30+V30)>0,IF(V30<S30,S30-V30," ")," ") | Z30: =IF((U30+V30)>0,IF(V30>S30,V30-S30," ")," ")
G31: =IF(E31>0,E31-F31," ") | H31: =H$29 -> 0.33 | I31: =IF(E31>0,MIN(E31*H31,G31)," ") | J31: =IF(E31>0,F31+I31," ") | K31: =IF(E31>0,E31-J31," ") | R31: =IF(O31>0,O31*R$4," ") | S31: =IF(O31>0,O31-R31," ") | W31: =IF(V31>0,E31," ") | X31: =IF(V31>0,J31," ") | Y31: =IF((U31+V31)>0,IF(V31<S31,S31-V31," ")," ") | Z31: =IF((U31+V31)>0,IF(V31>S31,V31-S31," ")," ")
G32: =IF(E32>0,E32-F32," ") | H32: =H$29 -> 0.33 | I32: =IF(E32>0,MIN(E32*H32,G32)," ") | J32: =IF(E32>0,F32+I32," ") | K32: =IF(E32>0,E32-J32," ") | R32: =IF(O32>0,O32*R$4," ") | S32: =IF(O32>0,O32-R32," ") | W32: =IF(V32>0,E32," ") | X32: =IF(V32>0,J32," ") | Y32: =IF((U32+V32)>0,IF(V32<S32,S32-V32," ")," ") | Z32: =IF((U32+V32)>0,IF(V32>S32,V32-S32," ")," ")
G33: =IF(E33>0,E33-F33," ") | H33: =H$29 -> 0.33 | I33: =IF(E33>0,MIN(E33*H33,G33)," ") | J33: =IF(E33>0,F33+I33," ") | K33: =IF(E33>0,E33-J33," ") | R33: =IF(O33>0,O33*R$4," ") | S33: =IF(O33>0,O33-R33," ") | W33: =IF(V33>0,E33," ") | X33: =IF(V33>0,J33," ") | Y33: =IF((U33+V33)>0,IF(V33<S33,S33-V33," ")," ") | Z33: =IF((U33+V33)>0,IF(V33>S33,V33-S33," ")," ")
G34: =IF(E34>0,E34-F34," ") | H34: =H$29 -> 0.33 | I34: =IF(E34>0,MIN(E34*H34,G34)," ") | J34: =IF(E34>0,F34+I34," ") | K34: =IF(E34>0,E34-J34," ") | R34: =IF(O34>0,O34*R$4," ") | S34: =IF(O34>0,O34-R34," ") | W34: =IF(V34>0,E34," ") | X34: =IF(V34>0,J34," ") | Y34: =IF((U34+V34)>0,IF(V34<S34,S34-V34," ")," ") | Z34: =IF((U34+V34)>0,IF(V34>S34,V34-S34," ")," ")
B35: Existing Computers | E35: =SUM(E30:E34) -> 0 | F35: =SUM(F30:F34) -> 0 | G35: =SUM(G30:G34) -> 0 | I35: =SUM(I30:I34) -> 0 | J35: =SUM(J30:J34) -> 0 | K35: =SUM(K30:K34) -> 0 | O35: =SUM(O30:O34) -> 0 | Q35: =SUM(Q30:Q34) -> 0 | R35: =SUM(R30:R34) -> 0 | S35: =SUM(S30:S34) -> 0 | V35: =SUM(V30:V34) -> 0 | W35: =SUM(W30:W34) -> 0 | X35: =SUM(X30:X34) -> 0 | Y35: =SUM(Y30:Y34) -> 0 | Z35: =SUM(Z30:Z34) -> 0
B37: Motor Vehicles - costing over £ | D37: =[1]Admin!$E$8 -> 12000 | H37: =[1]Admin!$G$17 -> 0.25
G38: =IF(E38>0,E38-F38," ") | H38: =H$37 -> 0.25 | I38: =IF(E38>0,MIN(E38*H38,G38)," ") | J38: =IF(E38>0,F38+I38," ") | K38: =IF(E38>0,E38-J38," ") | M38: 0 | R38: =IF(O38>0,MIN(O38*R$4*(1-M38),[1]Admin!$G$8*(1-M38))," ") | S38: =IF(O38>0,O38-R38," ") | W38: =IF(V38>0,E38," ") | X38: =IF(V38>0,J38," ") | Y38: =IF((U38+V38)>0,IF(V38<S38,(S38-V38)*(1-M38)," ")," ") | Z38: =IF((U38+V38)>0,IF(V38>S38,(V38-S38)*(1-M38)," ")," ")
G39: =IF(E39>0,E39-F39," ") | H39: =H$37 -> 0.25 | I39: =IF(E39>0,MIN(E39*H39,G39)," ") | J39: =IF(E39>0,F39+I39," ") | K39: =IF(E39>0,E39-J39," ") | M39: 0 | R39: =IF(O39>0,MIN(O39*R$4*(1-M39),[1]Admin!$G$8*(1-M39))," ") | S39: =IF(O39>0,O39-R39," ") | W39: =IF(V39>0,E39," ") | X39: =IF(V39>0,J39," ") | Y39: =IF((U39+V39)>0,IF(V39<S39,(S39-V39)*(1-M39)," ")," ") | Z39: =IF((U39+V39)>0,IF(V39>S39,(V39-S39)*(1-M39)," ")," ")
G40: =IF(E40>0,E40-F40," ") | H40: =H$37 -> 0.25 | I40: =IF(E40>0,MIN(E40*H40,G40)," ") | J40: =IF(E40>0,F40+I40," ") | K40: =IF(E40>0,E40-J40," ") | M40: 0 | R40: =IF(O40>0,MIN(O40*R$4*(1-M40),[1]Admin!$G$8*(1-M40))," ") | S40: =IF(O40>0,O40-R40," ") | W40: =IF(V40>0,E40," ") | X40: =IF(V40>0,J40," ") | Y40: =IF((U40+V40)>0,IF(V40<S40,(S40-V40)*(1-M40)," ")," ") | Z40: =IF((U40+V40)>0,IF(V40>S40,(V40-S40)*(1-M40)," ")," ")
G41: =IF(E41>0,E41-F41," ") | H41: =H$37 -> 0.25 | I41: =IF(E41>0,MIN(E41*H41,G41)," ") | J41: =IF(E41>0,F41+I41," ") | K41: =IF(E41>0,E41-J41," ") | M41: 0 | R41: =IF(O41>0,MIN(O41*R$4*(1-M41),[1]Admin!$G$8*(1-M41))," ") | S41: =IF(O41>0,O41-R41," ") | W41: =IF(V41>0,E41," ") | X41: =IF(V41>0,J41," ") | Y41: =IF((U41+V41)>0,IF(V41<S41,(S41-V41)*(1-M41)," ")," ") | Z41: =IF((U41+V41)>0,IF(V41>S41,(V41-S41)*(1-M41)," ")," ")
G42: =IF(E42>0,E42-F42," ") | H42: =H$37 -> 0.25 | I42: =IF(E42>0,MIN(E42*H42,G42)," ") | J42: =IF(E42>0,F42+I42," ") | K42: =IF(E42>0,E42-J42," ") | M42: 0 | R42: =IF(O42>0,MIN(O42*R$4*(1-M42),[1]Admin!$G$8*(1-M42))," ") | S42: =IF(O42>0,O42-R42," ") | W42: =IF(V42>0,E42," ") | X42: =IF(V42>0,J42," ") | Y42: =IF((U42+V42)>0,IF(V42<S42,(S42-V42)*(1-M42)," ")," ") | Z42: =IF((U42+V42)>0,IF(V42>S42,(V42-S42)*(1-M42)," ")," ")
B43: Motor Vehicles - costing under £ | D43: =[1]Admin!$E$8 -> 12000
G44: =IF(E44>0,E44-F44," ") | H44: =H$37 -> 0.25 | I44: =IF(E44>0,MIN(E44*H44,G44)," ") | J44: =IF(E44>0,F44+I44," ") | K44: =IF(E44>0,E44-J44," ") | M44: 0 | R44: =IF(O44>0,MIN(O44*R$4*(1-M44),[1]Admin!$G$8*(1-M44))," ") | S44: =IF(O44>0,O44-R44," ") | W44: =IF(V44>0,E44," ") | X44: =IF(V44>0,J44," ") | Y44: =IF((U44+V44)>0,IF(V44<S44,(S44-V44)*(1-M44)," ")," ") | Z44: =IF((U44+V44)>0,IF(V44>S44,(V44-S44)*(1-M44)," ")," ")
G45: =IF(E45>0,E45-F45," ") | H45: =H$37 -> 0.25 | I45: =IF(E45>0,MIN(E45*H45,G45)," ") | J45: =IF(E45>0,F45+I45," ") | K45: =IF(E45>0,E45-J45," ") | M45: 0 | R45: =IF(O45>0,MIN(O45*R$4*(1-M45),[1]Admin!$G$8*(1-M45))," ") | S45: =IF(O45>0,O45-R45," ") | W45: =IF(V45>0,E45," ") | X45: =IF(V45>0,J45," ") | Y45: =IF((U45+V45)>0,IF(V45<S45,(S45-V45)*(1-M45)," ")," ") | Z45: =IF((U45+V45)>0,IF(V45>S45,(V45-S45)*(1-M45)," ")," ")
G46: =IF(E46>0,E46-F46," ") | H46: =H$37 -> 0.25 | I46: =IF(E46>0,MIN(E46*H46,G46)," ") | J46: =IF(E46>0,F46+I46," ") | K46: =IF(E46>0,E46-J46," ") | M46: 0 | R46: =IF(O46>0,MIN(O46*R$4*(1-M46),[1]Admin!$G$8*(1-M46))," ") | S46: =IF(O46>0,O46-R46," ") | W46: =IF(V46>0,E46," ") | X46: =IF(V46>0,J46," ") | Y46: =IF((U46+V46)>0,IF(V46<S46,(S46-V46)*(1-M46)," ")," ") | Z46: =IF((U46+V46)>0,IF(V46>S46,(V46-S46)*(1-M46)," ")," ")
G47: =IF(E47>0,E47-F47," ") | H47: =H$37 -> 0.25 | I47: =IF(E47>0,MIN(E47*H47,G47)," ") | J47: =IF(E47>0,F47+I47," ") | K47: =IF(E47>0,E47-J47," ") | M47: 0 | R47: =IF(O47>0,MIN(O47*R$4*(1-M47),[1]Admin!$G$8*(1-M47))," ") | S47: =IF(O47>0,O47-R47," ") | W47: =IF(V47>0,E47," ") | X47: =IF(V47>0,J47," ") | Y47: =IF((U47+V47)>0,IF(V47<S47,(S47-V47)*(1-M47)," ")," ") | Z47: =IF((U47+V47)>0,IF(V47>S47,(V47-S47)*(1-M47)," ")," ")
G48: =IF(E48>0,E48-F48," ") | H48: =H$37 -> 0.25 | I48: =IF(E48>0,MIN(E48*H48,G48)," ") | J48: =IF(E48>0,F48+I48," ") | K48: =IF(E48>0,E48-J48," ") | M48: 0 | R48: =IF(O48>0,MIN(O48*R$4*(1-M48),[1]Admin!$G$8*(1-M48))," ") | S48: =IF(O48>0,O48-R48," ") | W48: =IF(V48>0,E48," ") | X48: =IF(V48>0,J48," ") | Y48: =IF((U48+V48)>0,IF(V48<S48,(S48-V48)*(1-M48)," ")," ") | Z48: =IF((U48+V48)>0,IF(V48>S48,(V48-S48)*(1-M48)," ")," ")
B49: Motor Vehicles - Vans & Lorries
G50: =IF(E50>0,E50-F50," ") | H50: =H$37 -> 0.25 | I50: =IF(E50>0,MIN(E50*H50,G50)," ") | J50: =IF(E50>0,F50+I50," ") | K50: =IF(E50>0,E50-J50," ") | M50: 0 | R50: =IF(O50>0,O50*R$4," ") | S50: =IF(O50>0,O50-R50," ") | W50: =IF(V50>0,E50," ") | X50: =IF(V50>0,J50," ") | Y50: =IF((U50+V50)>0,IF(V50<S50,(S50-V50)*(1-M50)," ")," ") | Z50: =IF((U50+V50)>0,IF(V50>S50,(V50-S50)*(1-M50)," ")," ")
G51: =IF(E51>0,E51-F51," ") | H51: =H$37 -> 0.25 | I51: =IF(E51>0,MIN(E51*H51,G51)," ") | J51: =IF(E51>0,F51+I51," ") | K51: =IF(E51>0,E51-J51," ") | M51: 0 | R51: =IF(O51>0,O51*R$4," ") | S51: =IF(O51>0,O51-R51," ") | W51: =IF(V51>0,E51," ") | X51: =IF(V51>0,J51," ") | Y51: =IF((U51+V51)>0,IF(V51<S51,(S51-V51)*(1-M51)," ")," ") | Z51: =IF((U51+V51)>0,IF(V51>S51,(V51-S51)*(1-M51)," ")," ")
G52: =IF(E52>0,E52-F52," ") | H52: =H$37 -> 0.25 | I52: =IF(E52>0,MIN(E52*H52,G52)," ") | J52: =IF(E52>0,F52+I52," ") | K52: =IF(E52>0,E52-J52," ") | M52: 0 | R52: =IF(O52>0,O52*R$4," ") | S52: =IF(O52>0,O52-R52," ") | W52: =IF(V52>0,E52," ") | X52: =IF(V52>0,J52," ") | Y52: =IF((U52+V52)>0,IF(V52<S52,(S52-V52)*(1-M52)," ")," ") | Z52: =IF((U52+V52)>0,IF(V52>S52,(V52-S52)*(1-M52)," ")," ")
G53: =IF(E53>0,E53-F53," ") | H53: =H$37 -> 0.25 | I53: =IF(E53>0,MIN(E53*H53,G53)," ") | J53: =IF(E53>0,F53+I53," ") | K53: =IF(E53>0,E53-J53," ") | M53: 0 | R53: =IF(O53>0,O53*R$4," ") | S53: =IF(O53>0,O53-R53," ") | W53: =IF(V53>0,E53," ") | X53: =IF(V53>0,J53," ") | Y53: =IF((U53+V53)>0,IF(V53<S53,(S53-V53)*(1-M53)," ")," ") | Z53: =IF((U53+V53)>0,IF(V53>S53,(V53-S53)*(1-M53)," ")," ")
G54: =IF(E54>0,E54-F54," ") | H54: =H$37 -> 0.25 | I54: =IF(E54>0,MIN(E54*H54,G54)," ") | J54: =IF(E54>0,F54+I54," ") | K54: =IF(E54>0,E54-J54," ") | M54: 0 | R54: =IF(O54>0,O54*R$4," ") | S54: =IF(O54>0,O54-R54," ") | W54: =IF(V54>0,E54," ") | X54: =IF(V54>0,J54," ") | Y54: =IF((U54+V54)>0,IF(V54<S54,(S54-V54)*(1-M54)," ")," ") | Z54: =IF((U54+V54)>0,IF(V54>S54,(V54-S54)*(1-M54)," ")," ")
B55: Existing Motor Vehicles | E55: =SUM(E38:E54) -> 0 | F55: =SUM(F38:F54) -> 0 | G55: =SUM(G38:G54) -> 0 | I55: =SUM(I38:I54) -> 0 | J55: =SUM(J38:J54) -> 0 | K55: =SUM(K38:K54) -> 0 | O55: =SUM(O38:O54) -> 0 | Q55: =SUM(Q38:Q54) -> 0 | R55: =SUM(R38:R54) -> 0 | S55: =SUM(S38:S54) -> 0 | V55: =SUM(V38:V54) -> 0 | W55: =SUM(W38:W54) -> 0 | X55: =SUM(X38:X54) -> 0 | Y55: =SUM(Y38:Y54) -> 0 | Z55: =SUM(Z38:Z54) -> 0
B57: =B6 -> EXISTING FIXED ASSETS at | D57: =D6 -> 45388 | E57: =E11+E19+E27+E35+E55 -> 0 | F57: =F11+F19+F27+F35+F55 -> 0 | G57: =G11+G19+G27+G35+G55 -> 0 | I57: =I11+I19+I27+I35+I55 -> 0 | J57: =J11+J19+J27+J35+J55 -> 0 | K57: =K11+K19+K27+K35+K55 -> 0 | O57: =O11+O19+O27+O35+O55 -> 0 | Q57: =Q11+Q19+Q27+Q35+Q55 -> 0 | R57: =R11+R19+R27+R35+R55 -> 0 | S57: =S11+S19+S27+S35+S55 -> 0 | V57: =V11+V19+V27+V35+V55 -> 0 | W57: =W11+W19+W27+W35+W55 -> 0 | X57: =X11+X19+X27+X35+X55 -> 0 | Y57: =Y11+Y19+Y27+Y35+Y55 -> 0 | Z57: =Z11+Z19+Z27+Z35+Z55 -> 0
B59: NEW FIXED ASSETS Bought AFTER | D59: =[1]Admin!$B$4 -> 45388
B60: Land & Property | H60: =H$7 -> 0
H61: =H$60 -> 0 | I61: =IF(E61>0,MIN(E61*H61,G61)," ") | J61: =IF(E61>0,F61+I61," ") | K61: =IF(E61>0,E61-J61," ") | W61: =IF(V61>0,E61," ") | X61: =IF(V61>0,J61," ")
H62: =H$60 -> 0 | I62: =IF(E62>0,MIN(E62*H62,G62)," ") | J62: =IF(E62>0,F62+I62," ") | K62: =IF(E62>0,E62-J62," ") | W62: =IF(V62>0,E62," ") | X62: =IF(V62>0,J62," ")
H63: =H$60 -> 0 | I63: =IF(E63>0,MIN(E63*H63,G63)," ") | J63: =IF(E63>0,F63+I63," ") | K63: =IF(E63>0,E63-J63," ") | W63: =IF(V63>0,E63," ") | X63: =IF(V63>0,J63," ")
B64: New Land & Property | E64: =SUM(E61:E63) -> 0 | F64: =SUM(F61:F63) -> 0 | G64: =SUM(G61:G63) -> 0 | I64: =SUM(I61:I63) -> 0 | J64: =SUM(J61:J63) -> 0 | K64: =SUM(K61:K63) -> 0 | O64: =SUM(O61:O63) -> 0 | Q64: =SUM(Q61:Q63) -> 0 | R64: =SUM(R61:R63) -> 0 | S64: =SUM(S61:S63) -> 0 | V64: =SUM(V61:V63) -> 0 | W64: =SUM(W61:W63) -> 0 | X64: =SUM(X61:X63) -> 0 | Y64: =SUM(Y61:Y63) -> 0 | Z64: =SUM(Z61:Z63) -> 0
B66: Plant & Machinery | H66: =H$13 -> 0.1
H67: =H$66 -> 0.1 | I67: =IF(E67>0,MIN(E67*H67,G67)," ") | J67: =IF(E67>0,F67+I67," ") | K67: =IF(E67>0,E67-J67," ") | P67: =P$4 -> 1 | Q67: =IF(E67>0,E67*P67," ") | S67: =IF(E67>0,E67-Q67," ") | W67: =IF(V67>0,E67," ") | X67: =IF(V67>0,J67," ") | Y67: =IF((U67+V67)>0,IF(V67<S67,S67-V67," ")," ") | Z67: =IF((U67+V67)>0,IF(V67>S67,V67-S67," ")," ")
H68: =H$66 -> 0.1 | I68: =IF(E68>0,MIN(E68*H68,G68)," ") | J68: =IF(E68>0,F68+I68," ") | K68: =IF(E68>0,E68-J68," ") | P68: =P$4 -> 1 | Q68: =IF(E68>0,E68*P68," ") | S68: =IF(E68>0,E68-Q68," ") | W68: =IF(V68>0,E68," ") | X68: =IF(V68>0,J68," ") | Y68: =IF((U68+V68)>0,IF(V68<S68,S68-V68," ")," ") | Z68: =IF((U68+V68)>0,IF(V68>S68,V68-S68," ")," ")
H69: =H$66 -> 0.1 | I69: =IF(E69>0,MIN(E69*H69,G69)," ") | J69: =IF(E69>0,F69+I69," ") | K69: =IF(E69>0,E69-J69," ") | P69: =P$4 -> 1 | Q69: =IF(E69>0,E69*P69," ") | S69: =IF(E69>0,E69-Q69," ") | W69: =IF(V69>0,E69," ") | X69: =IF(V69>0,J69," ") | Y69: =IF((U69+V69)>0,IF(V69<S69,S69-V69," ")," ") | Z69: =IF((U69+V69)>0,IF(V69>S69,V69-S69," ")," ")
H70: =H$66 -> 0.1 | I70: =IF(E70>0,MIN(E70*H70,G70)," ") | J70: =IF(E70>0,F70+I70," ") | K70: =IF(E70>0,E70-J70," ") | P70: =P$4 -> 1 | Q70: =IF(E70>0,E70*P70," ") | S70: =IF(E70>0,E70-Q70," ") | W70: =IF(V70>0,E70," ") | X70: =IF(V70>0,J70," ") | Y70: =IF((U70+V70)>0,IF(V70<S70,S70-V70," ")," ") | Z70: =IF((U70+V70)>0,IF(V70>S70,V70-S70," ")," ")
H71: =H$66 -> 0.1 | I71: =IF(E71>0,MIN(E71*H71,G71)," ") | J71: =IF(E71>0,F71+I71," ") | K71: =IF(E71>0,E71-J71," ") | P71: =P$4 -> 1 | Q71: =IF(E71>0,E71*P71," ") | S71: =IF(E71>0,E71-Q71," ") | W71: =IF(V71>0,E71," ") | X71: =IF(V71>0,J71," ") | Y71: =IF((U71+V71)>0,IF(V71<S71,S71-V71," ")," ") | Z71: =IF((U71+V71)>0,IF(V71>S71,V71-S71," ")," ")
B72: New Plant & Machinery | E72: =SUM(E67:E71) -> 0 | F72: =SUM(F67:F71) -> 0 | G72: =SUM(G67:G71) -> 0 | I72: =SUM(I67:I71) -> 0 | J72: =SUM(J67:J71) -> 0 | K72: =SUM(K67:K71) -> 0 | O72: =SUM(O67:O71) -> 0 | Q72: =SUM(Q67:Q71) -> 0 | R72: =SUM(R67:R71) -> 0 | S72: =SUM(S67:S71) -> 0 | V72: =SUM(V67:V71) -> 0 | W72: =SUM(W67:W71) -> 0 | X72: =SUM(X67:X71) -> 0 | Y72: =SUM(Y67:Y71) -> 0 | Z72: =SUM(Z67:Z71) -> 0
B74: Fixtures & Fittings | H74: =H$21 -> 0.2
H75: =H$74 -> 0.2 | I75: =IF(E75>0,MIN(E75*H75,G75)," ") | J75: =IF(E75>0,F75+I75," ") | K75: =IF(E75>0,E75-J75," ") | P75: =P$4 -> 1 | Q75: =IF(E75>0,E75*P75," ") | S75: =IF(E75>0,E75-Q75," ") | W75: =IF(V75>0,E75," ") | X75: =IF(V75>0,J75," ") | Y75: =IF((U75+V75)>0,IF(V75<S75,S75-V75," ")," ") | Z75: =IF((U75+V75)>0,IF(V75>S75,V75-S75," ")," ")
H76: =H$74 -> 0.2 | I76: =IF(E76>0,MIN(E76*H76,G76)," ") | J76: =IF(E76>0,F76+I76," ") | K76: =IF(E76>0,E76-J76," ") | P76: =P$4 -> 1 | Q76: =IF(E76>0,E76*P76," ") | S76: =IF(E76>0,E76-Q76," ") | W76: =IF(V76>0,E76," ") | X76: =IF(V76>0,J76," ") | Y76: =IF((U76+V76)>0,IF(V76<S76,S76-V76," ")," ") | Z76: =IF((U76+V76)>0,IF(V76>S76,V76-S76," ")," ")
H77: =H$74 -> 0.2 | I77: =IF(E77>0,MIN(E77*H77,G77)," ") | J77: =IF(E77>0,F77+I77," ") | K77: =IF(E77>0,E77-J77," ") | P77: =P$4 -> 1 | Q77: =IF(E77>0,E77*P77," ") | S77: =IF(E77>0,E77-Q77," ") | W77: =IF(V77>0,E77," ") | X77: =IF(V77>0,J77," ") | Y77: =IF((U77+V77)>0,IF(V77<S77,S77-V77," ")," ") | Z77: =IF((U77+V77)>0,IF(V77>S77,V77-S77," ")," ")
H78: =H$74 -> 0.2 | I78: =IF(E78>0,MIN(E78*H78,G78)," ") | J78: =IF(E78>0,F78+I78," ") | K78: =IF(E78>0,E78-J78," ") | P78: =P$4 -> 1 | Q78: =IF(E78>0,E78*P78," ") | S78: =IF(E78>0,E78-Q78," ") | W78: =IF(V78>0,E78," ") | X78: =IF(V78>0,J78," ") | Y78: =IF((U78+V78)>0,IF(V78<S78,S78-V78," ")," ") | Z78: =IF((U78+V78)>0,IF(V78>S78,V78-S78," ")," ")
H79: =H$74 -> 0.2 | I79: =IF(E79>0,MIN(E79*H79,G79)," ") | J79: =IF(E79>0,F79+I79," ") | K79: =IF(E79>0,E79-J79," ") | P79: =P$4 -> 1 | Q79: =IF(E79>0,E79*P79," ") | S79: =IF(E79>0,E79-Q79," ") | W79: =IF(V79>0,E79," ") | X79: =IF(V79>0,J79," ") | Y79: =IF((U79+V79)>0,IF(V79<S79,S79-V79," ")," ") | Z79: =IF((U79+V79)>0,IF(V79>S79,V79-S79," ")," ")
B80: New Fixtures & Fittings | E80: =SUM(E75:E79) -> 0 | F80: =SUM(F75:F79) -> 0 | G80: =SUM(G75:G79) -> 0 | I80: =SUM(I75:I79) -> 0 | J80: =SUM(J75:J79) -> 0 | K80: =SUM(K75:K79) -> 0 | O80: =SUM(O75:O79) -> 0 | Q80: =SUM(Q75:Q79) -> 0 | R80: =SUM(R75:R79) -> 0 | S80: =SUM(S75:S79) -> 0 | V80: =SUM(V75:V79) -> 0 | W80: =SUM(W75:W79) -> 0 | X80: =SUM(X75:X79) -> 0 | Y80: =SUM(Y75:Y79) -> 0 | Z80: =SUM(Z75:Z79) -> 0
B82: Computers | H82: =H$29 -> 0.33
H83: =H$82 -> 0.33 | I83: =IF(E83>0,MIN(E83*H83,G83)," ") | J83: =IF(E83>0,F83+I83," ") | K83: =IF(E83>0,E83-J83," ") | P83: =P$4 -> 1 | Q83: =IF(E83>0,E83*P83," ") | S83: =IF(E83>0,E83-Q83," ") | W83: =IF(V83>0,E83," ") | X83: =IF(V83>0,J83," ") | Y83: =IF((U83+V83)>0,IF(V83<S83,S83-V83," ")," ") | Z83: =IF((U83+V83)>0,IF(V83>S83,V83-S83," ")," ")
H84: =H$82 -> 0.33 | I84: =IF(E84>0,MIN(E84*H84,G84)," ") | J84: =IF(E84>0,F84+I84," ") | K84: =IF(E84>0,E84-J84," ") | P84: =P$4 -> 1 | Q84: =IF(E84>0,E84*P84," ") | S84: =IF(E84>0,E84-Q84," ") | W84: =IF(V84>0,E84," ") | X84: =IF(V84>0,J84," ") | Y84: =IF((U84+V84)>0,IF(V84<S84,S84-V84," ")," ") | Z84: =IF((U84+V84)>0,IF(V84>S84,V84-S84," ")," ")
H85: =H$82 -> 0.33 | I85: =IF(E85>0,MIN(E85*H85,G85)," ") | J85: =IF(E85>0,F85+I85," ") | K85: =IF(E85>0,E85-J85," ") | P85: =P$4 -> 1 | Q85: =IF(E85>0,E85*P85," ") | S85: =IF(E85>0,E85-Q85," ") | W85: =IF(V85>0,E85," ") | X85: =IF(V85>0,J85," ") | Y85: =IF((U85+V85)>0,IF(V85<S85,S85-V85," ")," ") | Z85: =IF((U85+V85)>0,IF(V85>S85,V85-S85," ")," ")
H86: =H$82 -> 0.33 | I86: =IF(E86>0,MIN(E86*H86,G86)," ") | J86: =IF(E86>0,F86+I86," ") | K86: =IF(E86>0,E86-J86," ") | P86: =P$4 -> 1 | Q86: =IF(E86>0,E86*P86," ") | S86: =IF(E86>0,E86-Q86," ") | W86: =IF(V86>0,E86," ") | X86: =IF(V86>0,J86," ") | Y86: =IF((U86+V86)>0,IF(V86<S86,S86-V86," ")," ") | Z86: =IF((U86+V86)>0,IF(V86>S86,V86-S86," ")," ")
H87: =H$82 -> 0.33 | I87: =IF(E87>0,MIN(E87*H87,G87)," ") | J87: =IF(E87>0,F87+I87," ") | K87: =IF(E87>0,E87-J87," ") | P87: =P$4 -> 1 | Q87: =IF(E87>0,E87*P87," ") | S87: =IF(E87>0,E87-Q87," ") | W87: =IF(V87>0,E87," ") | X87: =IF(V87>0,J87," ") | Y87: =IF((U87+V87)>0,IF(V87<S87,S87-V87," ")," ") | Z87: =IF((U87+V87)>0,IF(V87>S87,V87-S87," ")," ")
B88: New Computers | E88: =SUM(E83:E87) -> 0 | F88: =SUM(F83:F87) -> 0 | G88: =SUM(G83:G87) -> 0 | I88: =SUM(I83:I87) -> 0 | J88: =SUM(J83:J87) -> 0 | K88: =SUM(K83:K87) -> 0 | O88: =SUM(O83:O87) -> 0 | Q88: =SUM(Q83:Q87) -> 0 | R88: =SUM(R83:R87) -> 0 | S88: =SUM(S83:S87) -> 0 | V88: =SUM(V83:V87) -> 0 | W88: =SUM(W83:W87) -> 0 | X88: =SUM(X83:X87) -> 0 | Y88: =SUM(Y83:Y87) -> 0 | Z88: =SUM(Z83:Z87) -> 0
B90: =B37 -> Motor Vehicles - costing over £ | D90: =D37 -> 12000 | H90: =H$37 -> 0.25
H91: =H$90 -> 0.25 | I91: =IF(E91>0,MIN(E91*H91,G91)," ") | J91: =IF(E91>0,F91+I91," ") | K91: =IF(E91>0,E91-J91," ") | M91: 0 | R91: =IF(E91>0,MIN(E91*R$4*(1-M91),[1]Admin!$G$8*(1-M91))," ") | S91: =IF(E91>0,E91-R91," ") | W91: =IF(V91>0,E91," ") | X91: =IF(V91>0,J91," ") | Y91: =IF((U91+V91)>0,IF(V91<S91,(S91-V91)*(1-M91)," ")," ") | Z91: =IF((U91+V91)>0,IF(V91>S91,(V91-S91)*(1-M91)," ")," ")
H92: =H$90 -> 0.25 | I92: =IF(E92>0,MIN(E92*H92,G92)," ") | J92: =IF(E92>0,F92+I92," ") | K92: =IF(E92>0,E92-J92," ") | M92: 0 | R92: =IF(E92>0,MIN(E92*R$4*(1-M92),[1]Admin!$G$8*(1-M92))," ") | S92: =IF(E92>0,E92-R92," ") | W92: =IF(V92>0,E92," ") | X92: =IF(V92>0,J92," ") | Y92: =IF((U92+V92)>0,IF(V92<S92,(S92-V92)*(1-M92)," ")," ") | Z92: =IF((U92+V92)>0,IF(V92>S92,(V92-S92)*(1-M92)," ")," ")
H93: =H$90 -> 0.25 | I93: =IF(E93>0,MIN(E93*H93,G93)," ") | J93: =IF(E93>0,F93+I93," ") | K93: =IF(E93>0,E93-J93," ") | M93: 0 | R93: =IF(E93>0,MIN(E93*R$4*(1-M93),[1]Admin!$G$8*(1-M93))," ") | S93: =IF(E93>0,E93-R93," ") | W93: =IF(V93>0,E93," ") | X93: =IF(V93>0,J93," ") | Y93: =IF((U93+V93)>0,IF(V93<S93,(S93-V93)*(1-M93)," ")," ") | Z93: =IF((U93+V93)>0,IF(V93>S93,(V93-S93)*(1-M93)," ")," ")
H94: =H$90 -> 0.25 | I94: =IF(E94>0,MIN(E94*H94,G94)," ") | J94: =IF(E94>0,F94+I94," ") | K94: =IF(E94>0,E94-J94," ") | M94: 0 | R94: =IF(E94>0,MIN(E94*R$4*(1-M94),[1]Admin!$G$8*(1-M94))," ") | S94: =IF(E94>0,E94-R94," ") | W94: =IF(V94>0,E94," ") | X94: =IF(V94>0,J94," ") | Y94: =IF((U94+V94)>0,IF(V94<S94,(S94-V94)*(1-M94)," ")," ") | Z94: =IF((U94+V94)>0,IF(V94>S94,(V94-S94)*(1-M94)," ")," ")
H95: =H$90 -> 0.25 | I95: =IF(E95>0,MIN(E95*H95,G95)," ") | J95: =IF(E95>0,F95+I95," ") | K95: =IF(E95>0,E95-J95," ") | M95: 0 | R95: =IF(E95>0,MIN(E95*R$4*(1-M95),[1]Admin!$G$8*(1-M95))," ") | S95: =IF(E95>0,E95-R95," ") | W95: =IF(V95>0,E95," ") | X95: =IF(V95>0,J95," ") | Y95: =IF((U95+V95)>0,IF(V95<S95,(S95-V95)*(1-M95)," ")," ") | Z95: =IF((U95+V95)>0,IF(V95>S95,(V95-S95)*(1-M95)," ")," ")
B96: =B43 -> Motor Vehicles - costing under £ | D96: =D43 -> 12000
H97: =H$90 -> 0.25 | I97: =IF(E97>0,MIN(E97*H97,G97)," ") | J97: =IF(E97>0,F97+I97," ") | K97: =IF(E97>0,E97-J97," ") | M97: 0 | R97: =IF(E97>0,MIN(E97*R$4*(1-M97),[1]Admin!$G$8*(1-M97))," ") | S97: =IF(E97>0,E97-R97," ") | W97: =IF(V97>0,E97," ") | X97: =IF(V97>0,J97," ") | Y97: =IF((U97+V97)>0,IF(V97<S97,(S97-V97)*(1-M97)," ")," ") | Z97: =IF((U97+V97)>0,IF(V97>S97,(V97-S97)*(1-M97)," ")," ")
H98: =H$90 -> 0.25 | I98: =IF(E98>0,MIN(E98*H98,G98)," ") | J98: =IF(E98>0,F98+I98," ") | K98: =IF(E98>0,E98-J98," ") | M98: 0 | R98: =IF(E98>0,MIN(E98*R$4*(1-M98),[1]Admin!$G$8*(1-M98))," ") | S98: =IF(E98>0,E98-R98," ") | W98: =IF(V98>0,E98," ") | X98: =IF(V98>0,J98," ") | Y98: =IF((U98+V98)>0,IF(V98<S98,(S98-V98)*(1-M98)," ")," ") | Z98: =IF((U98+V98)>0,IF(V98>S98,(V98-S98)*(1-M98)," ")," ")
H99: =H$90 -> 0.25 | I99: =IF(E99>0,MIN(E99*H99,G99)," ") | J99: =IF(E99>0,F99+I99," ") | K99: =IF(E99>0,E99-J99," ") | M99: 0 | R99: =IF(E99>0,MIN(E99*R$4*(1-M99),[1]Admin!$G$8*(1-M99))," ") | S99: =IF(E99>0,E99-R99," ") | W99: =IF(V99>0,E99," ") | X99: =IF(V99>0,J99," ") | Y99: =IF((U99+V99)>0,IF(V99<S99,(S99-V99)*(1-M99)," ")," ") | Z99: =IF((U99+V99)>0,IF(V99>S99,(V99-S99)*(1-M99)," ")," ")
H100: =H$90 -> 0.25 | I100: =IF(E100>0,MIN(E100*H100,G100)," ") | J100: =IF(E100>0,F100+I100," ") | K100: =IF(E100>0,E100-J100," ") | M100: 0 | R100: =IF(E100>0,MIN(E100*R$4*(1-M100),[1]Admin!$G$8*(1-M100))," ") | S100: =IF(E100>0,E100-R100," ") | W100: =IF(V100>0,E100," ") | X100: =IF(V100>0,J100," ") | Y100: =IF((U100+V100)>0,IF(V100<S100,(S100-V100)*(1-M100)," ")," ") | Z100: =IF((U100+V100)>0,IF(V100>S100,(V100-S100)*(1-M100)," ")," ")
H101: =H$90 -> 0.25 | I101: =IF(E101>0,MIN(E101*H101,G101)," ") | J101: =IF(E101>0,F101+I101," ") | K101: =IF(E101>0,E101-J101," ") | M101: 0 | R101: =IF(E101>0,MIN(E101*R$4*(1-M101),[1]Admin!$G$8*(1-M101))," ") | S101: =IF(E101>0,E101-R101," ") | W101: =IF(V101>0,E101," ") | X101: =IF(V101>0,J101," ") | Y101: =IF((U101+V101)>0,IF(V101<S101,(S101-V101)*(1-M101)," ")," ") | Z101: =IF((U101+V101)>0,IF(V101>S101,(V101-S101)*(1-M101)," ")," ")
B102: Motor Vehicles - Vans & Lorries
H103: =H$90 -> 0.25 | I103: =IF(E103>0,MIN(E103*H103,G103)," ") | J103: =IF(E103>0,F103+I103," ") | K103: =IF(E103>0,E103-J103," ") | M103: 0 | P103: =P$4 -> 1 | Q103: =IF(E103>0,E103*P103," ") | S103: =IF(E103>0,E103-Q103," ") | W103: =IF(V103>0,E103," ") | X103: =IF(V103>0,J103," ") | Y103: =IF((U103+V103)>0,IF(V103<S103,(S103-V103)*(1-M103)," ")," ") | Z103: =IF((U103+V103)>0,IF(V103>S103,(V103-S103)*(1-M103)," ")," ")
H104: =H$90 -> 0.25 | I104: =IF(E104>0,MIN(E104*H104,G104)," ") | J104: =IF(E104>0,F104+I104," ") | K104: =IF(E104>0,E104-J104," ") | M104: 0 | P104: =P$4 -> 1 | Q104: =IF(E104>0,E104*P104," ") | S104: =IF(E104>0,E104-Q104," ") | W104: =IF(V104>0,E104," ") | X104: =IF(V104>0,J104," ") | Y104: =IF((U104+V104)>0,IF(V104<S104,(S104-V104)*(1-M104)," ")," ") | Z104: =IF((U104+V104)>0,IF(V104>S104,(V104-S104)*(1-M104)," ")," ")
H105: =H$90 -> 0.25 | I105: =IF(E105>0,MIN(E105*H105,G105)," ") | J105: =IF(E105>0,F105+I105," ") | K105: =IF(E105>0,E105-J105," ") | M105: 0 | P105: =P$4 -> 1 | Q105: =IF(E105>0,E105*P105," ") | S105: =IF(E105>0,E105-Q105," ") | W105: =IF(V105>0,E105," ") | X105: =IF(V105>0,J105," ") | Y105: =IF((U105+V105)>0,IF(V105<S105,(S105-V105)*(1-M105)," ")," ") | Z105: =IF((U105+V105)>0,IF(V105>S105,(V105-S105)*(1-M105)," ")," ")
H106: =H$90 -> 0.25 | I106: =IF(E106>0,MIN(E106*H106,G106)," ") | J106: =IF(E106>0,F106+I106," ") | K106: =IF(E106>0,E106-J106," ") | M106: 0 | P106: =P$4 -> 1 | Q106: =IF(E106>0,E106*P106," ") | S106: =IF(E106>0,E106-Q106," ") | W106: =IF(V106>0,E106," ") | X106: =IF(V106>0,J106," ") | Y106: =IF((U106+V106)>0,IF(V106<S106,(S106-V106)*(1-M106)," ")," ") | Z106: =IF((U106+V106)>0,IF(V106>S106,(V106-S106)*(1-M106)," ")," ")
H107: =H$90 -> 0.25 | I107: =IF(E107>0,MIN(E107*H107,G107)," ") | J107: =IF(E107>0,F107+I107," ") | K107: =IF(E107>0,E107-J107," ") | M107: 0 | P107: =P$4 -> 1 | Q107: =IF(E107>0,E107*P107," ") | S107: =IF(E107>0,E107-Q107," ") | W107: =IF(V107>0,E107," ") | X107: =IF(V107>0,J107," ") | Y107: =IF((U107+V107)>0,IF(V107<S107,(S107-V107)*(1-M107)," ")," ") | Z107: =IF((U107+V107)>0,IF(V107>S107,(V107-S107)*(1-M107)," ")," ")
B108: New Motor Vehicles | E108: =SUM(E91:E107) -> 0 | F108: =SUM(F91:F107) -> 0 | G108: =SUM(G91:G107) -> 0 | I108: =SUM(I91:I107) -> 0 | J108: =SUM(J91:J107) -> 0 | K108: =SUM(K91:K107) -> 0 | O108: =SUM(O91:O107) -> 0 | Q108: =SUM(Q91:Q107) -> 0 | R108: =SUM(R91:R107) -> 0 | S108: =SUM(S91:S107) -> 0 | V108: =SUM(V91:V107) -> 0 | W108: =SUM(W91:W107) -> 0 | X108: =SUM(X91:X107) -> 0 | Y108: =SUM(Y91:Y107) -> 0 | Z108: =SUM(Z91:Z107) -> 0
B110: =B59 -> NEW FIXED ASSETS Bought AFTER | D110: =D59 -> 45388 | E110: =E64+E72+E80+E88+E108 -> 0 | F110: =F64+F72+F80+F88+F108 -> 0 | G110: =G64+G72+G80+G88+G108 -> 0 | I110: =I64+I72+I80+I88+I108 -> 0 | J110: =J64+J72+J80+J88+J108 -> 0 | K110: =K64+K72+K80+K88+K108 -> 0 | O110: =O64+O72+O80+O88+O108 -> 0 | Q110: =Q64+Q72+Q80+Q88+Q108 -> 0 | R110: =R64+R72+R80+R88+R108 -> 0 | S110: =S64+S72+S80+S88+S108 -> 0 | V110: =V64+V72+V80+V88+V108 -> 0 | W110: =W64+W72+W80+W88+W108 -> 0 | X110: =X64+X72+X80+X88+X108 -> 0 | Y110: =Y64+Y72+Y80+Y88+Y108 -> 0 | Z110: =Z64+Z72+Z80+Z88+Z108 -> 0

Sheet FAreconciliation
E2: FIXED ASSET RECONCILIATION
B4: FIXED ASSET PURCHASES | E4: Original Cost | G4: FIXED ASSET SALES | K4: Sales Value | M4: Reconciliation totals on Row 15 should be zero. If Row 15 not zero check all Fixed Assets entered on Purhases and Sales Spreadsheets have been recorded on the Fixed Asset Schedule.
B5: Fixed Asset Schedule New Additions | G5: Fixed Asset Schedule Assets Sold
B6: New Land & Property | E6: =Schedule!E64 -> 0 | G6: Land & Property Sold | K6: =Schedule!V11+Schedule!V64 -> 0
B7: New Plant & Machinery | E7: =Schedule!E72 -> 0 | G7: Plant & Machinery Sold | K7: =Schedule!V19+Schedule!V72 -> 0
B8: New Fixtures & Fittings | E8: =Schedule!E80 -> 0 | G8: Fixtures & Fittings Sold | K8: =Schedule!V27+Schedule!V80 -> 0
B9: New Computers | E9: =Schedule!E88 -> 0 | G9: Computers Sold | K9: =Schedule!V35+Schedule!V88 -> 0
B10: New Motor Vehicles | E10: =Schedule!E108 -> 0 | G10: Motor Vehicles Sold | K10: =Schedule!V55+Schedule!V108 -> 0
B11: FIXED ASSETS SCHEDULE | E11: =SUM(E6:E10) -> 0 | G11: FIXED ASSETS SCHEDULE | K11: =SUM(K6:K10) -> 0
B13: PURCHASE SHEET FIXED ASSETS PURCHASES | E13: =[2]Mar!$AB$2 -> 0 | G13: SALES SHEET FIXED ASSETS SALES | K13: =[3]Mar!$V$2 -> 0
B15: =IF(E15>0,"Purchases exceed Assets listed on Schedule",IF(E15<0,"Assets listed on Schedule exceed Purchase values","Purchases reconcile with Fixed asset Schedule")) -> Purchases reconcile with Fixed asset Schedule | E15: =E13-E11 -> 0 | G15: =IF(K15>0,"Sales exceed Assets listed on Schedule",IF(K15<0,"Assets listed on Schedule exceed Sales values","Sales reconcile with Fixed asset Schedule")) -> Sales reconcile with Fixed asset Schedule | K15: =K13-K11 -> 0

Sheet HPfinance
C2: YEAR END LONG TERM CREDITORS | E2: =SUM(E8:E14) -> 0 | G2: Enter Finance Agreements due to end more than 12 months after the financial year end or leave blank
B3: New Hire Purchase Agreements
B5: Agreement Date | C5: Finance Company | D5: Agreement Refernce | E5: Total Amount Financed excluding Admin & Interest | F5: Admin Charges | G5: Total Interest Charged | H5: Number of Months | I5: BANK ANALYSIS PURPOSES | L5: Enter Supplier Name as entered on Purchase Spreadsheet
I6: Monthly Payment | J6: Net Capital Repayment | K6: Monthly Interest
I8: =IF(E8>0,(E8+F8+G8)/H8," ") | J8: =IF(H8>0,I8-K8," ") | K8: =IF(H8>0,G8/H8," ")
I10: =IF(H10>0,#REF!/H10," ") | J10: =IF(H10>0,I10-K10," ") | K10: =IF(H10>0,G10/H10," ")
I12: =IF(H12>0,#REF!/H12," ") | J12: =IF(H12>0,I12-K12," ") | K12: =IF(H12>0,G12/H12," ")
I14: =IF(H14>0,#REF!/H14," ") | J14: =IF(H14>0,I14-K14," ") | K14: =IF(H14>0,G14/H14," ")
B17: Hire Purchase Agreements existing at start of financial year | H17: Required to calculate monthly interest liability
B19: Agreement Date | C19: Finance Company | D19: Agreement Refernce | E19: Total Amount Financed excluding Admin & Interest | F19: Admin Charges | G19: Total Interest Charged | H19: Number of Months | I19: BANK ANALYSIS PURPOSES | L19: Enter Supplier Name as entered on Purchase Spreadsheet
I20: Monthly Payment | J20: Net Capital Repayment | K20: Monthly Interest
I22: =IF(E22>0,(E22+F22+G22)/H22," ") | J22: =IF(H22>0,I22-K22," ") | K22: =IF(H22>0,G22/H22," ")
I24: =IF(H24>0,#REF!/H24," ") | J24: =IF(H24>0,I24-K24," ") | K24: =IF(H24>0,G24/H24," ")
I26: =IF(H26>0,#REF!/H26," ") | J26: =IF(H26>0,I26-K26," ") | K26: =IF(H26>0,G26/H26," ")
I28: =IF(H28>0,#REF!/H28," ") | J28: =IF(H28>0,I28-K28," ") | K28: =IF(H28>0,G28/H28," ")
