Workbook

Sheet VATQtr1
B2: Value Added Tax Return | K2: =[1]Admin!$B$5 -> 45777
E3: Copy values in boxes to your Vat return | K3: =[1]Admin!$B$6 -> 45808
B4: To calculate vat payable 1.Click Cell G5 Vat Period 2.Click down arrow 3.Select Vat quarter end date | K4: =[1]Admin!$B$7 -> 45838
E5: VAT Period ends | G5: 46234 | K5: =[1]Admin!$B$8 -> 45869
K6: =[1]Admin!$B$9 -> 45900
E7: Due date: | G7: =LOOKUP(G$5,Vatinterface!B:B,Vatinterface!C:C) -> 46203 | K7: =[1]Admin!$B$10 -> 45930
K8: =[1]Admin!$B$11 -> 45961
B9: VAT due on sales | F9: 1 | G9: =LOOKUP(G$5,Vatinterface!B:B,Vatinterface!G:G) -> 0 | K9: =[1]Admin!$B$12 -> 45991
K10: =[1]Admin!$B$13 -> 46022
B11: VAT due on purchases from other EU states | F11: 2 | G11: 0 | K11: =[1]Admin!$B$14 -> 46053
K12: =[1]Admin!$B$15 -> 46081
B13: VAT due on sales | F13: 3 | G13: =G9+G11 -> 0 | K13: =[1]Admin!$B$16 -> 46112
K14: =[1]Admin!$B$18 -> 46142
B15: VAT reclaimed on purchases | F15: 4 | G15: =LOOKUP(G$5,Vatinterface!B:B,Vatinterface!K:K) -> 0 | K15: =[1]Admin!$B$19 -> 46173
B17: =IF(G17>0,"Net VAT to be PAID to Customs","Net VAT to be RECLIAMED from Customs") -> Net VAT to be RECLIAMED from Customs | F17: 5 | G17: =G13-G15 -> 0
B19: =IF(LOOKUP(G$5,Vatinterface!B:B,Vatinterface!M:M)>0,"FLAT RATE SCHEME APPLIED"," ") | E19: =IF(LOOKUP(G$5,Vatinterface!B:B,Vatinterface!M:M)>0,LOOKUP(G$5,Vatinterface!B:B,Vatinterface!M:M)," ")
B21: =IF(LOOKUP(G$5,Vatinterface!B:B,Vatinterface!M:M)>0,"Total value of sales including VAT","Total value of sales excluding VAT") -> Total value of sales excluding VAT | F21: 6 | G21: =IF(LOOKUP(G$5,Vatinterface!B:B,Vatinterface!M:M)>0,(LOOKUP(G$5,Vatinterface!B:B,Vatinterface!E:E)+LOOKUP(G$5,Vatinterface!B:B,Vatinterface!G:G)),LOOKUP(G$5,Vatinterface!B:B,Vatinterface!E:E)) -> 0
B23: Total value of purchases excluding VAT | F23: 7 | G23: =LOOKUP(G$5,Vatinterface!B:B,Vatinterface!I:I) -> 0
A25: Note: | B25: Box 2 is set to zero, any amounts due should be calculated and inserted manually
B26: If goods are bought or sold to other EU states boxes 8 & 9 on the return will require completion
A28: Vat returns must be received by HM Customs & Excise on or before the due date to avoid surcharges
A29: Make cheques payable to "H M Customs and Excise" and write your VAT registration number on the back
A30: Quote your VAT registration number as a reference if paying direct by bank
A31: Account Name: HMCE VAT: Account No: 52055000 Sort Code: 10 00 00

Sheet VATQtr2
B2: Value Added Tax Return | K2: =[1]Admin!$B$5 -> 45777
E3: Copy values in boxes to your Vat return | K3: =[1]Admin!$B$6 -> 45808
B4: To calculate vat payable 1.Click Cell G5 Vat Period 2.Click down arrow 3.Select Vat quarter end date | K4: =[1]Admin!$B$7 -> 45838
E5: VAT Period ends | G5: 46326 | K5: =[1]Admin!$B$8 -> 45869
K6: =[1]Admin!$B$9 -> 45900
E7: Due date: | G7: =LOOKUP(G$5,Vatinterface!B:B,Vatinterface!C:C) -> 46203 | K7: =[1]Admin!$B$10 -> 45930
K8: =[1]Admin!$B$11 -> 45961
B9: VAT due on sales | F9: 1 | G9: =LOOKUP(G$5,Vatinterface!B:B,Vatinterface!G:G) -> 0 | K9: =[1]Admin!$B$12 -> 45991
K10: =[1]Admin!$B$13 -> 46022
B11: VAT due on purchases from other EU states | F11: 2 | G11: 0 | K11: =[1]Admin!$B$14 -> 46053
K12: =[1]Admin!$B$15 -> 46081
B13: VAT due on sales | F13: 3 | G13: =G9+G11 -> 0 | K13: =[1]Admin!$B$16 -> 46112
K14: =[1]Admin!$B$18 -> 46142
B15: VAT reclaimed on purchases | F15: 4 | G15: =LOOKUP(G$5,Vatinterface!B:B,Vatinterface!K:K) -> 0 | K15: =[1]Admin!$B$19 -> 46173
B17: =IF(G17>0,"Net VAT to be PAID to Customs","Net VAT to be RECLIAMED from Customs") -> Net VAT to be RECLIAMED from Customs | F17: 5 | G17: =G13-G15 -> 0
B19: =IF(LOOKUP(G$5,Vatinterface!B:B,Vatinterface!M:M)>0,"FLAT RATE SCHEME APPLIED"," ") | E19: =IF(LOOKUP(G$5,Vatinterface!B:B,Vatinterface!M:M)>0,LOOKUP(G$5,Vatinterface!B:B,Vatinterface!M:M)," ")
B21: =IF(LOOKUP(G$5,Vatinterface!B:B,Vatinterface!M:M)>0,"Total value of sales including VAT","Total value of sales excluding VAT") -> Total value of sales excluding VAT | F21: 6 | G21: =IF(LOOKUP(G$5,Vatinterface!B:B,Vatinterface!M:M)>0,(LOOKUP(G$5,Vatinterface!B:B,Vatinterface!E:E)+LOOKUP(G$5,Vatinterface!B:B,Vatinterface!G:G)),LOOKUP(G$5,Vatinterface!B:B,Vatinterface!E:E)) -> 0
B23: Total value of purchases excluding VAT | F23: 7 | G23: =LOOKUP(G$5,Vatinterface!B:B,Vatinterface!I:I) -> 0
A25: Note: | B25: Box 2 is set to zero, any amounts due should be calculated and inserted manually
B26: If goods are bought or sold to other EU states boxes 8 & 9 on the return will require completion
A28: Vat returns must be received by HM Customs & Excise on or before the due date to avoid surcharges
A29: Make cheques payable to "H M Customs and Excise" and write your VAT registration number on the back
A30: Quote your VAT registration number as a reference if paying direct by bank
A31: Account Name: HMCE VAT: Account No: 52055000 Sort Code: 10 00 00

Sheet VATQtr3
B2: Value Added Tax Return | K2: =[1]Admin!$B$5 -> 45777
E3: Copy values in boxes to your Vat return | K3: =[1]Admin!$B$6 -> 45808
B4: To calculate vat payable 1.Click Cell G5 Vat Period 2.Click down arrow 3.Select Vat quarter end date | K4: =[1]Admin!$B$7 -> 45838
E5: VAT Period ends | G5: 46418 | K5: =[1]Admin!$B$8 -> 45869
K6: =[1]Admin!$B$9 -> 45900
E7: Due date: | G7: =LOOKUP(G$5,Vatinterface!B:B,Vatinterface!C:C) -> 46203 | K7: =[1]Admin!$B$10 -> 45930
K8: =[1]Admin!$B$11 -> 45961
B9: VAT due on sales | F9: 1 | G9: =LOOKUP(G$5,Vatinterface!B:B,Vatinterface!G:G) -> 0 | K9: =[1]Admin!$B$12 -> 45991
K10: =[1]Admin!$B$13 -> 46022
B11: VAT due on purchases from other EU states | F11: 2 | G11: 0 | K11: =[1]Admin!$B$14 -> 46053
K12: =[1]Admin!$B$15 -> 46081
B13: VAT due on sales | F13: 3 | G13: =G9+G11 -> 0 | K13: =[1]Admin!$B$16 -> 46112
K14: =[1]Admin!$B$18 -> 46142
B15: VAT reclaimed on purchases | F15: 4 | G15: =LOOKUP(G$5,Vatinterface!B:B,Vatinterface!K:K) -> 0 | K15: =[1]Admin!$B$19 -> 46173
B17: =IF(G17>0,"Net VAT to be PAID to Customs","Net VAT to be RECLIAMED from Customs") -> Net VAT to be RECLIAMED from Customs | F17: 5 | G17: =G13-G15 -> 0
B19: =IF(LOOKUP(G$5,Vatinterface!B:B,Vatinterface!M:M)>0,"FLAT RATE SCHEME APPLIED"," ") | E19: =IF(LOOKUP(G$5,Vatinterface!B:B,Vatinterface!M:M)>0,LOOKUP(G$5,Vatinterface!B:B,Vatinterface!M:M)," ")
B21: =IF(LOOKUP(G$5,Vatinterface!B:B,Vatinterface!M:M)>0,"Total value of sales including VAT","Total value of sales excluding VAT") -> Total value of sales excluding VAT | F21: 6 | G21: =IF(LOOKUP(G$5,Vatinterface!B:B,Vatinterface!M:M)>0,(LOOKUP(G$5,Vatinterface!B:B,Vatinterface!E:E)+LOOKUP(G$5,Vatinterface!B:B,Vatinterface!G:G)),LOOKUP(G$5,Vatinterface!B:B,Vatinterface!E:E)) -> 0
B23: Total value of purchases excluding VAT | F23: 7 | G23: =LOOKUP(G$5,Vatinterface!B:B,Vatinterface!I:I) -> 0
A25: Note: | B25: Box 2 is set to zero, any amounts due should be calculated and inserted manually
B26: If goods are bought or sold to other EU states boxes 8 & 9 on the return will require completion
A28: Vat returns must be received by HM Customs & Excise on or before the due date to avoid surcharges
A29: Make cheques payable to "H M Customs and Excise" and write your VAT registration number on the back
A30: Quote your VAT registration number as a reference if paying direct by bank
A31: Account Name: HMCE VAT: Account No: 52055000 Sort Code: 10 00 00

Sheet VATQtr4
B2: Value Added Tax Return | K2: =[1]Admin!$B$5 -> 45777
E3: Copy values in boxes to your Vat return | K3: =[1]Admin!$B$6 -> 45808
B4: To calculate vat payable 1.Click Cell G5 Vat Period 2.Click down arrow 3.Select Vat quarter end date | K4: =[1]Admin!$B$7 -> 45838
E5: VAT Period ends | G5: 46507 | K5: =[1]Admin!$B$8 -> 45869
K6: =[1]Admin!$B$9 -> 45900
E7: Due date: | G7: =LOOKUP(G$5,Vatinterface!B:B,Vatinterface!C:C) -> 46203 | K7: =[1]Admin!$B$10 -> 45930
K8: =[1]Admin!$B$11 -> 45961
B9: VAT due on sales | F9: 1 | G9: =LOOKUP(G$5,Vatinterface!B:B,Vatinterface!G:G) -> 0 | K9: =[1]Admin!$B$12 -> 45991
K10: =[1]Admin!$B$13 -> 46022
B11: VAT due on purchases from other EU states | F11: 2 | G11: 0 | K11: =[1]Admin!$B$14 -> 46053
K12: =[1]Admin!$B$15 -> 46081
B13: VAT due on sales | F13: 3 | G13: =G9+G11 -> 0 | K13: =[1]Admin!$B$16 -> 46112
K14: =[1]Admin!$B$18 -> 46142
B15: VAT reclaimed on purchases | F15: 4 | G15: =LOOKUP(G$5,Vatinterface!B:B,Vatinterface!K:K) -> 0 | K15: =[1]Admin!$B$19 -> 46173
B17: =IF(G17>0,"Net VAT to be PAID to Customs","Net VAT to be RECLIAMED from Customs") -> Net VAT to be RECLIAMED from Customs | F17: 5 | G17: =G13-G15 -> 0
B19: =IF(LOOKUP(G$5,Vatinterface!B:B,Vatinterface!M:M)>0,"FLAT RATE SCHEME APPLIED"," ") | E19: =IF(LOOKUP(G$5,Vatinterface!B:B,Vatinterface!M:M)>0,LOOKUP(G$5,Vatinterface!B:B,Vatinterface!M:M)," ")
B21: =IF(LOOKUP(G$5,Vatinterface!B:B,Vatinterface!M:M)>0,"Total value of sales including VAT","Total value of sales excluding VAT") -> Total value of sales excluding VAT | F21: 6 | G21: =IF(LOOKUP(G$5,Vatinterface!B:B,Vatinterface!M:M)>0,(LOOKUP(G$5,Vatinterface!B:B,Vatinterface!E:E)+LOOKUP(G$5,Vatinterface!B:B,Vatinterface!G:G)),LOOKUP(G$5,Vatinterface!B:B,Vatinterface!E:E)) -> 0
B23: Total value of purchases excluding VAT | F23: 7 | G23: =LOOKUP(G$5,Vatinterface!B:B,Vatinterface!I:I) -> 0
A25: Note: | B25: Box 2 is set to zero, any amounts due should be calculated and inserted manually
B26: If goods are bought or sold to other EU states boxes 8 & 9 on the return will require completion
A28: Vat returns must be received by HM Customs & Excise on or before the due date to avoid surcharges
A29: Make cheques payable to "H M Customs and Excise" and write your VAT registration number on the back
A30: Quote your VAT registration number as a reference if paying direct by bank
A31: Account Name: HMCE VAT: Account No: 52055000 Sort Code: 10 00 00

Sheet VATQtr5
B2: Value Added Tax Return | K2: =[1]Admin!$B$5 -> 45777
E3: Copy values in boxes to your Vat return | K3: =[1]Admin!$B$6 -> 45808
B4: To calculate vat payable 1.Click Cell G5 Vat Period 2.Click down arrow 3.Select Vat quarter end date | K4: =[1]Admin!$B$7 -> 45838
E5: VAT Period ends | G5: 46538 | K5: =[1]Admin!$B$8 -> 45869
K6: =[1]Admin!$B$9 -> 45900
E7: Due date: | G7: =LOOKUP(G$5,Vatinterface!B:B,Vatinterface!C:C) -> 46203 | K7: =[1]Admin!$B$10 -> 45930
K8: =[1]Admin!$B$11 -> 45961
B9: VAT due on sales | F9: 1 | G9: =LOOKUP(G$5,Vatinterface!B:B,Vatinterface!G:G) -> 0 | K9: =[1]Admin!$B$12 -> 45991
K10: =[1]Admin!$B$13 -> 46022
B11: VAT due on purchases from other EU states | F11: 2 | G11: 0 | K11: =[1]Admin!$B$14 -> 46053
K12: =[1]Admin!$B$15 -> 46081
B13: VAT due on sales | F13: 3 | G13: =G9+G11 -> 0 | K13: =[1]Admin!$B$16 -> 46112
K14: =[1]Admin!$B$18 -> 46142
B15: VAT reclaimed on purchases | F15: 4 | G15: =LOOKUP(G$5,Vatinterface!B:B,Vatinterface!K:K) -> 0 | K15: =[1]Admin!$B$19 -> 46173
B17: =IF(G17>0,"Net VAT to be PAID to Customs","Net VAT to be RECLIAMED from Customs") -> Net VAT to be RECLIAMED from Customs | F17: 5 | G17: =G13-G15 -> 0
B19: =IF(LOOKUP(G$5,Vatinterface!B:B,Vatinterface!M:M)>0,"FLAT RATE SCHEME APPLIED"," ") | E19: =IF(LOOKUP(G$5,Vatinterface!B:B,Vatinterface!M:M)>0,LOOKUP(G$5,Vatinterface!B:B,Vatinterface!M:M)," ")
B21: =IF(LOOKUP(G$5,Vatinterface!B:B,Vatinterface!M:M)>0,"Total value of sales including VAT","Total value of sales excluding VAT") -> Total value of sales excluding VAT | F21: 6 | G21: =IF(LOOKUP(G$5,Vatinterface!B:B,Vatinterface!M:M)>0,(LOOKUP(G$5,Vatinterface!B:B,Vatinterface!E:E)+LOOKUP(G$5,Vatinterface!B:B,Vatinterface!G:G)),LOOKUP(G$5,Vatinterface!B:B,Vatinterface!E:E)) -> 0
B23: Total value of purchases excluding VAT | F23: 7 | G23: =LOOKUP(G$5,Vatinterface!B:B,Vatinterface!I:I) -> 0
A25: Note: | B25: Box 2 is set to zero, any amounts due should be calculated and inserted manually
B26: If goods are bought or sold to other EU states boxes 8 & 9 on the return will require completion
A28: Vat returns must be received by HM Customs & Excise on or before the due date to avoid surcharges
A29: Make cheques payable to "H M Customs and Excise" and write your VAT registration number on the back
A30: Quote your VAT registration number as a reference if paying direct by bank
A31: Account Name: HMCE VAT: Account No: 52055000 Sort Code: 10 00 00

Sheet Vatinterface
B2: Vat Period End | C2: Final Date for Vat Payment | D2: Month Sales | E2: Quarter Sales Net of Vat | F2: Month Vat Output | G2: Quarter Vat Due Sales | H2: Month Purchases | I2: Quarter Purchases Net of vat | J2: Month Vat Input | K2: Quarter Vat Reclaimed Purchases | M2: Flat rate Scheme Applied
B4: =[1]Admin!$B$2 -> 45716 | C4: =B5 -> 45747 | D4: =S02Y1!$G$1 -> 0 | F4: =S02Y1!$F$1 -> 0 | H4: =P02Y1!$I$1 -> 0 | J4: =P02Y1!$H$1 -> 0 | M4: =IF([2]Apr!$H$4>0,[2]Apr!$H$4,0) -> 0
B5: =[1]Admin!$B$3 -> 45747 | C5: =B6 -> 45777 | D5: =S03Y1!$G$1 -> 0 | F5: =S03Y1!$F$1 -> 0 | H5: =P03Y1!$I$1 -> 0 | J5: =P03Y1!$H$1 -> 0 | M5: =IF([2]Apr!$H$4>0,[2]Apr!$H$4,0) -> 0
B6: =[1]Admin!$B$5 -> 45777 | C6: =B7 -> 45808 | D6: =[2]Apr!$I$1 -> 0 | E6: =SUM(D4:D6) -> 0 | F6: =[2]Apr!$H$1 -> 0 | G6: =SUM(F4:F6) -> 0 | H6: =[3]Apr!$I$1 -> 0 | I6: =SUM(H4:H6) -> 0 | J6: =[3]Apr!$H$1 -> 0 | K6: =SUM(J4:J6) -> 0 | M6: =IF([2]Apr!$H$4>0,[2]Apr!$H$4,0) -> 0
B7: =[1]Admin!$B$6 -> 45808 | C7: =B8 -> 45838 | D7: =[2]May!$I$1 -> 0 | E7: =SUM(D5:D7) -> 0 | F7: =[2]May!$H$1 -> 0 | G7: =SUM(F5:F7) -> 0 | H7: =[3]May!$I$1 -> 0 | I7: =SUM(H5:H7) -> 0 | J7: =[3]May!$H$1 -> 0 | K7: =SUM(J5:J7) -> 0 | M7: =IF([2]May!$H$4>0,[2]May!$H$4,0) -> 0
B8: =[1]Admin!$B$7 -> 45838 | C8: =B9 -> 45869 | D8: =[2]Jun!$I$1 -> 0 | E8: =SUM(D6:D8) -> 0 | F8: =[2]Jun!$H$1 -> 0 | G8: =SUM(F6:F8) -> 0 | H8: =[3]Jun!$I$1 -> 0 | I8: =SUM(H6:H8) -> 0 | J8: =[3]Jun!$H$1 -> 0 | K8: =SUM(J6:J8) -> 0 | M8: =IF([2]Jun!$H$4>0,[2]Jun!$H$4,0) -> 0
B9: =[1]Admin!$B$8 -> 45869 | C9: =B10 -> 45900 | D9: =[2]Jul!$I$1 -> 0 | E9: =SUM(D7:D9) -> 0 | F9: =[2]Jul!$H$1 -> 0 | G9: =SUM(F7:F9) -> 0 | H9: =[3]Jul!$I$1 -> 0 | I9: =SUM(H7:H9) -> 0 | J9: =[3]Jul!$H$1 -> 0 | K9: =SUM(J7:J9) -> 0 | M9: =IF([2]Jul!$H$4>0,[2]Jul!$H$4,0) -> 0
B10: =[1]Admin!$B$9 -> 45900 | C10: =B11 -> 45930 | D10: =[2]Aug!$I$1 -> 0 | E10: =SUM(D8:D10) -> 0 | F10: =[2]Aug!$H$1 -> 0 | G10: =SUM(F8:F10) -> 0 | H10: =[3]Aug!$I$1 -> 0 | I10: =SUM(H8:H10) -> 0 | J10: =[3]Aug!$H$1 -> 0 | K10: =SUM(J8:J10) -> 0 | M10: =IF([2]Aug!$H$4>0,[2]Aug!$H$4,0) -> 0
B11: =[1]Admin!$B$10 -> 45930 | C11: =B12 -> 45961 | D11: =[2]Sep!$I$1 -> 0 | E11: =SUM(D9:D11) -> 0 | F11: =[2]Sep!$H$1 -> 0 | G11: =SUM(F9:F11) -> 0 | H11: =[3]Sep!$I$1 -> 0 | I11: =SUM(H9:H11) -> 0 | J11: =[3]Sep!$H$1 -> 0 | K11: =SUM(J9:J11) -> 0 | M11: =IF([2]Sep!$H$4>0,[2]Sep!$H$4,0) -> 0
B12: =[1]Admin!$B$11 -> 45961 | C12: =B13 -> 45991 | D12: =[2]Oct!$I$1 -> 0 | E12: =SUM(D10:D12) -> 0 | F12: =[2]Oct!$H$1 -> 0 | G12: =SUM(F10:F12) -> 0 | H12: =[3]Oct!$I$1 -> 0 | I12: =SUM(H10:H12) -> 0 | J12: =[3]Oct!$H$1 -> 0 | K12: =SUM(J10:J12) -> 0 | M12: =IF([2]Oct!$H$4>0,[2]Oct!$H$4,0) -> 0
B13: =[1]Admin!$B$12 -> 45991 | C13: =B14 -> 46022 | D13: =[2]Nov!$I$1 -> 0 | E13: =SUM(D11:D13) -> 0 | F13: =[2]Nov!$H$1 -> 0 | G13: =SUM(F11:F13) -> 0 | H13: =[3]Nov!$I$1 -> 0 | I13: =SUM(H11:H13) -> 0 | J13: =[3]Nov!$H$1 -> 0 | K13: =SUM(J11:J13) -> 0 | M13: =IF([2]Nov!$H$4>0,[2]Nov!$H$4,0) -> 0
B14: =[1]Admin!$B$13 -> 46022 | C14: =B15 -> 46053 | D14: =[2]Dec!$I$1 -> 0 | E14: =SUM(D12:D14) -> 0 | F14: =[2]Dec!$H$1 -> 0 | G14: =SUM(F12:F14) -> 0 | H14: =[3]Dec!$I$1 -> 0 | I14: =SUM(H12:H14) -> 0 | J14: =[3]Dec!$H$1 -> 0 | K14: =SUM(J12:J14) -> 0 | M14: =IF([2]Dec!$H$4>0,[2]Dec!$H$4,0) -> 0
B15: =[1]Admin!$B$14 -> 46053 | C15: =B16 -> 46081 | D15: =[2]Jan!$I$1 -> 0 | E15: =SUM(D13:D15) -> 0 | F15: =[2]Jan!$H$1 -> 0 | G15: =SUM(F13:F15) -> 0 | H15: =[3]Jan!$I$1 -> 0 | I15: =SUM(H13:H15) -> 0 | J15: =[3]Jan!$H$1 -> 0 | K15: =SUM(J13:J15) -> 0 | M15: =IF([2]Jan!$H$4>0,[2]Jan!$H$4,0) -> 0
B16: =[1]Admin!$B$15 -> 46081 | C16: =B17 -> 46112 | D16: =[2]Feb!$I$1 -> 0 | E16: =SUM(D14:D16) -> 0 | F16: =[2]Feb!$H$1 -> 0 | G16: =SUM(F14:F16) -> 0 | H16: =[3]Feb!$I$1 -> 0 | I16: =SUM(H14:H16) -> 0 | J16: =[3]Feb!$H$1 -> 0 | K16: =SUM(J14:J16) -> 0 | M16: =IF([2]Feb!$H$4>0,[2]Feb!$H$4,0) -> 0
B17: =[1]Admin!$B$16 -> 46112 | C17: =B18 -> 46142 | D17: =[2]Mar!$I$1 -> 0 | E17: =SUM(D15:D17) -> 0 | F17: =[2]Mar!$H$1 -> 0 | G17: =SUM(F15:F17) -> 0 | H17: =[3]Mar!$I$1 -> 0 | I17: =SUM(H15:H17) -> 0 | J17: =[3]Mar!$H$1 -> 0 | K17: =SUM(J15:J17) -> 0 | M17: =IF([2]Mar!$H$4>0,[2]Mar!$H$4,0) -> 0
B18: =[1]Admin!$B$18 -> 46142 | C18: =B19 -> 46173 | D18: =S04Y2!$G$1 -> 0 | E18: =SUM(D16:D18) -> 0 | F18: =S04Y2!$F$1 -> 0 | G18: =SUM(F16:F18) -> 0 | H18: =P04Y2!$I$1 -> 0 | I18: =SUM(H16:H18) -> 0 | J18: =P04Y2!$H$1 -> 0 | K18: =SUM(J16:J18) -> 0 | M18: =IF([2]Mar!$H$4>0,[2]Mar!$H$4,0) -> 0
B19: =[1]Admin!$B$19 -> 46173 | C19: =[1]Admin!$B$20 -> 46203 | D19: =S05Y2!$G$1 -> 0 | E19: =SUM(D17:D19) -> 0 | F19: =S05Y2!$F$1 -> 0 | G19: =SUM(F17:F19) -> 0 | H19: =P05Y2!$I$1 -> 0 | I19: =SUM(H17:H19) -> 0 | J19: =P05Y2!$H$1 -> 0 | K19: =SUM(J17:J19) -> 0 | M19: =IF([2]Mar!$H$4>0,[2]Mar!$H$4,0) -> 0

Sheet S02Y1
A1: USE FOR VAT PERIODS OUTSIDE FINANCIAL YEAR | C1: Total for Month | E1: =SUM(E5:E200) -> 0 | F1: =SUM(F5:F200) -> 0 | G1: =SUM(G5:G200) -> 0
A2: Sales Date | B2: Customer Name | C2: Sales Invoice Number or reference | E2: Sales Value including Vat | F2: =[2]OpeningDebtors!$H$2 -> 20 | G2: Sales Net of Vat
F3: Vat Output
F4: =[2]OpeningDebtors!$H$4 -> 0
F5: =IF(F$4>0,(IF(E5<>0,E5*F$4/100," ")),IF(E5<>0,E5*F$2/(100+F$2)," ")) | G5: =IF((E5<>0),E5-F5," ")
F6: =IF(F$4>0,(IF(E6<>0,E6*F$4/100," ")),IF(E6<>0,E6*F$2/(100+F$2)," ")) | G6: =IF((E6<>0),E6-F6," ")
F7: =IF(F$4>0,(IF(E7<>0,E7*F$4/100," ")),IF(E7<>0,E7*F$2/(100+F$2)," ")) | G7: =IF((E7<>0),E7-F7," ")
F8: =IF(F$4>0,(IF(E8<>0,E8*F$4/100," ")),IF(E8<>0,E8*F$2/(100+F$2)," ")) | G8: =IF((E8<>0),E8-F8," ")
F9: =IF(F$4>0,(IF(E9<>0,E9*F$4/100," ")),IF(E9<>0,E9*F$2/(100+F$2)," ")) | G9: =IF((E9<>0),E9-F9," ")
F10: =IF(F$4>0,(IF(E10<>0,E10*F$4/100," ")),IF(E10<>0,E10*F$2/(100+F$2)," ")) | G10: =IF((E10<>0),E10-F10," ")
F11: =IF(F$4>0,(IF(E11<>0,E11*F$4/100," ")),IF(E11<>0,E11*F$2/(100+F$2)," ")) | G11: =IF((E11<>0),E11-F11," ")
F12: =IF(F$4>0,(IF(E12<>0,E12*F$4/100," ")),IF(E12<>0,E12*F$2/(100+F$2)," ")) | G12: =IF((E12<>0),E12-F12," ")
F13: =IF(F$4>0,(IF(E13<>0,E13*F$4/100," ")),IF(E13<>0,E13*F$2/(100+F$2)," ")) | G13: =IF((E13<>0),E13-F13," ")
F14: =IF(F$4>0,(IF(E14<>0,E14*F$4/100," ")),IF(E14<>0,E14*F$2/(100+F$2)," ")) | G14: =IF((E14<>0),E14-F14," ")
F15: =IF(F$4>0,(IF(E15<>0,E15*F$4/100," ")),IF(E15<>0,E15*F$2/(100+F$2)," ")) | G15: =IF((E15<>0),E15-F15," ")
F16: =IF(F$4>0,(IF(E16<>0,E16*F$4/100," ")),IF(E16<>0,E16*F$2/(100+F$2)," ")) | G16: =IF((E16<>0),E16-F16," ")
... F200: =IF(F$4>0,(IF(E200<>0,E200*F$4/100," ")),IF(E200<>0,E200*F$2/(100+F$2)," ")) | G200: =IF((E200<>0),E200-F200," ")
A201: Entries below this row are not included in Row 1 Totals

Sheet S03Y1
A1: USE FOR VAT PERIODS OUTSIDE FINANCIAL YEAR | C1: Total for Month | E1: =SUM(E5:E200) -> 0 | F1: =SUM(F5:F200) -> 0 | G1: =SUM(G5:G200) -> 0
A2: Sales Date | B2: Customer Name | C2: Sales Invoice Number or reference | E2: Sales Value including Vat | F2: =[2]OpeningDebtors!$H$2 -> 20 | G2: Sales Net of Vat
F3: Vat Output
F4: =[2]OpeningDebtors!$H$4 -> 0
F5: =IF(F$4>0,(IF(E5<>0,E5*F$4/100," ")),IF(E5<>0,E5*F$2/(100+F$2)," ")) | G5: =IF((E5<>0),E5-F5," ")
F6: =IF(F$4>0,(IF(E6<>0,E6*F$4/100," ")),IF(E6<>0,E6*F$2/(100+F$2)," ")) | G6: =IF((E6<>0),E6-F6," ")
F7: =IF(F$4>0,(IF(E7<>0,E7*F$4/100," ")),IF(E7<>0,E7*F$2/(100+F$2)," ")) | G7: =IF((E7<>0),E7-F7," ")
F8: =IF(F$4>0,(IF(E8<>0,E8*F$4/100," ")),IF(E8<>0,E8*F$2/(100+F$2)," ")) | G8: =IF((E8<>0),E8-F8," ")
F9: =IF(F$4>0,(IF(E9<>0,E9*F$4/100," ")),IF(E9<>0,E9*F$2/(100+F$2)," ")) | G9: =IF((E9<>0),E9-F9," ")
F10: =IF(F$4>0,(IF(E10<>0,E10*F$4/100," ")),IF(E10<>0,E10*F$2/(100+F$2)," ")) | G10: =IF((E10<>0),E10-F10," ")
F11: =IF(F$4>0,(IF(E11<>0,E11*F$4/100," ")),IF(E11<>0,E11*F$2/(100+F$2)," ")) | G11: =IF((E11<>0),E11-F11," ")
F12: =IF(F$4>0,(IF(E12<>0,E12*F$4/100," ")),IF(E12<>0,E12*F$2/(100+F$2)," ")) | G12: =IF((E12<>0),E12-F12," ")
F13: =IF(F$4>0,(IF(E13<>0,E13*F$4/100," ")),IF(E13<>0,E13*F$2/(100+F$2)," ")) | G13: =IF((E13<>0),E13-F13," ")
F14: =IF(F$4>0,(IF(E14<>0,E14*F$4/100," ")),IF(E14<>0,E14*F$2/(100+F$2)," ")) | G14: =IF((E14<>0),E14-F14," ")
F15: =IF(F$4>0,(IF(E15<>0,E15*F$4/100," ")),IF(E15<>0,E15*F$2/(100+F$2)," ")) | G15: =IF((E15<>0),E15-F15," ")
F16: =IF(F$4>0,(IF(E16<>0,E16*F$4/100," ")),IF(E16<>0,E16*F$2/(100+F$2)," ")) | G16: =IF((E16<>0),E16-F16," ")
... F200: =IF(F$4>0,(IF(E200<>0,E200*F$4/100," ")),IF(E200<>0,E200*F$2/(100+F$2)," ")) | G200: =IF((E200<>0),E200-F200," ")
A201: Entries below this row are not included in Row 1 Totals

Sheet S04Y2
A1: USE FOR VAT PERIODS OUTSIDE FINANCIAL YEAR | C1: Total for Month | E1: =SUM(E5:E200) -> 0 | F1: =SUM(F5:F200) -> 0 | G1: =SUM(G5:G200) -> 0
A2: Sales Date | B2: Customer Name | C2: Sales Invoice Number or reference | E2: Sales Value including Vat | F2: =[2]ClosingDebtors!$H$2 -> 20 | G2: Sales Net of Vat
F3: Vat Output
F4: =[2]ClosingDebtors!$H$4 -> 0
F5: =IF(F$4>0,(IF(E5<>0,E5*F$4/100," ")),IF(E5<>0,E5*F$2/(100+F$2)," ")) | G5: =IF((E5<>0),E5-F5," ")
F6: =IF(F$4>0,(IF(E6<>0,E6*F$4/100," ")),IF(E6<>0,E6*F$2/(100+F$2)," ")) | G6: =IF((E6<>0),E6-F6," ")
F7: =IF(F$4>0,(IF(E7<>0,E7*F$4/100," ")),IF(E7<>0,E7*F$2/(100+F$2)," ")) | G7: =IF((E7<>0),E7-F7," ")
F8: =IF(F$4>0,(IF(E8<>0,E8*F$4/100," ")),IF(E8<>0,E8*F$2/(100+F$2)," ")) | G8: =IF((E8<>0),E8-F8," ")
F9: =IF(F$4>0,(IF(E9<>0,E9*F$4/100," ")),IF(E9<>0,E9*F$2/(100+F$2)," ")) | G9: =IF((E9<>0),E9-F9," ")
F10: =IF(F$4>0,(IF(E10<>0,E10*F$4/100," ")),IF(E10<>0,E10*F$2/(100+F$2)," ")) | G10: =IF((E10<>0),E10-F10," ")
F11: =IF(F$4>0,(IF(E11<>0,E11*F$4/100," ")),IF(E11<>0,E11*F$2/(100+F$2)," ")) | G11: =IF((E11<>0),E11-F11," ")
F12: =IF(F$4>0,(IF(E12<>0,E12*F$4/100," ")),IF(E12<>0,E12*F$2/(100+F$2)," ")) | G12: =IF((E12<>0),E12-F12," ")
F13: =IF(F$4>0,(IF(E13<>0,E13*F$4/100," ")),IF(E13<>0,E13*F$2/(100+F$2)," ")) | G13: =IF((E13<>0),E13-F13," ")
F14: =IF(F$4>0,(IF(E14<>0,E14*F$4/100," ")),IF(E14<>0,E14*F$2/(100+F$2)," ")) | G14: =IF((E14<>0),E14-F14," ")
F15: =IF(F$4>0,(IF(E15<>0,E15*F$4/100," ")),IF(E15<>0,E15*F$2/(100+F$2)," ")) | G15: =IF((E15<>0),E15-F15," ")
F16: =IF(F$4>0,(IF(E16<>0,E16*F$4/100," ")),IF(E16<>0,E16*F$2/(100+F$2)," ")) | G16: =IF((E16<>0),E16-F16," ")
... F200: =IF(F$4>0,(IF(E200<>0,E200*F$4/100," ")),IF(E200<>0,E200*F$2/(100+F$2)," ")) | G200: =IF((E200<>0),E200-F200," ")
A201: Entries below this row are not included in Row 1 Totals

Sheet S05Y2
A1: USE FOR VAT PERIODS OUTSIDE FINANCIAL YEAR | C1: Total for Month | E1: =SUM(E5:E200) -> 0 | F1: =SUM(F5:F200) -> 0 | G1: =SUM(G5:G200) -> 0
A2: Sales Date | B2: Customer Name | C2: Sales Invoice Number or reference | E2: Sales Value including Vat | F2: =[2]ClosingDebtors!$H$2 -> 20 | G2: Sales Net of Vat
F3: Vat Output
F4: =[2]ClosingDebtors!$H$4 -> 0
F5: =IF(F$4>0,(IF(E5<>0,E5*F$4/100," ")),IF(E5<>0,E5*F$2/(100+F$2)," ")) | G5: =IF((E5<>0),E5-F5," ")
F6: =IF(F$4>0,(IF(E6<>0,E6*F$4/100," ")),IF(E6<>0,E6*F$2/(100+F$2)," ")) | G6: =IF((E6<>0),E6-F6," ")
F7: =IF(F$4>0,(IF(E7<>0,E7*F$4/100," ")),IF(E7<>0,E7*F$2/(100+F$2)," ")) | G7: =IF((E7<>0),E7-F7," ")
F8: =IF(F$4>0,(IF(E8<>0,E8*F$4/100," ")),IF(E8<>0,E8*F$2/(100+F$2)," ")) | G8: =IF((E8<>0),E8-F8," ")
F9: =IF(F$4>0,(IF(E9<>0,E9*F$4/100," ")),IF(E9<>0,E9*F$2/(100+F$2)," ")) | G9: =IF((E9<>0),E9-F9," ")
F10: =IF(F$4>0,(IF(E10<>0,E10*F$4/100," ")),IF(E10<>0,E10*F$2/(100+F$2)," ")) | G10: =IF((E10<>0),E10-F10," ")
F11: =IF(F$4>0,(IF(E11<>0,E11*F$4/100," ")),IF(E11<>0,E11*F$2/(100+F$2)," ")) | G11: =IF((E11<>0),E11-F11," ")
F12: =IF(F$4>0,(IF(E12<>0,E12*F$4/100," ")),IF(E12<>0,E12*F$2/(100+F$2)," ")) | G12: =IF((E12<>0),E12-F12," ")
F13: =IF(F$4>0,(IF(E13<>0,E13*F$4/100," ")),IF(E13<>0,E13*F$2/(100+F$2)," ")) | G13: =IF((E13<>0),E13-F13," ")
F14: =IF(F$4>0,(IF(E14<>0,E14*F$4/100," ")),IF(E14<>0,E14*F$2/(100+F$2)," ")) | G14: =IF((E14<>0),E14-F14," ")
F15: =IF(F$4>0,(IF(E15<>0,E15*F$4/100," ")),IF(E15<>0,E15*F$2/(100+F$2)," ")) | G15: =IF((E15<>0),E15-F15," ")
F16: =IF(F$4>0,(IF(E16<>0,E16*F$4/100," ")),IF(E16<>0,E16*F$2/(100+F$2)," ")) | G16: =IF((E16<>0),E16-F16," ")
... F200: =IF(F$4>0,(IF(E200<>0,E200*F$4/100," ")),IF(E200<>0,E200*F$2/(100+F$2)," ")) | G200: =IF((E200<>0),E200-F200," ")
A201: Entries below this row are not included in Row 1 Totals

Sheet P02Y1
A1: USE FOR VAT PERIODS OUTSIDE FINANCIAL YEAR | C1: Purchase Invoice Number or Reference | E1: Total for Month | G1: =SUM(G5:G200) -> 0 | H1: =SUM(H5:H200) -> 0 | I1: =SUM(I5:I200) -> 0
A2: Purchase Date | B2: =IF((I1-SUM(P1:AL1)<>0),"COMPLETE EXPENSE ANALYSIS by inserting expense letter in col F","Supplier") -> Supplier | E2: Purchase Description | G2: Total Purchase Value incl Vat | H2: =[3]OpeningCreditors!$H$2 -> 20 | I2: Purchases Net of Vat
H3: Vat Input
H5: =IF(G5<>0,G5*H$2/(100+H$2)," ") | I5: =IF((G5<>0),G5-H5," ")
H6: =IF(G6<>0,G6*H$2/(100+H$2)," ") | I6: =IF((G6<>0),G6-H6," ")
H7: =IF(G7<>0,G7*H$2/(100+H$2)," ") | I7: =IF((G7<>0),G7-H7," ")
H8: =IF(G8<>0,G8*H$2/(100+H$2)," ") | I8: =IF((G8<>0),G8-H8," ")
H9: =IF(G9<>0,G9*H$2/(100+H$2)," ") | I9: =IF((G9<>0),G9-H9," ")
H10: =IF(G10<>0,G10*H$2/(100+H$2)," ") | I10: =IF((G10<>0),G10-H10," ")
H11: =IF(G11<>0,G11*H$2/(100+H$2)," ") | I11: =IF((G11<>0),G11-H11," ")
H12: =IF(G12<>0,G12*H$2/(100+H$2)," ") | I12: =IF((G12<>0),G12-H12," ")
H13: =IF(G13<>0,G13*H$2/(100+H$2)," ") | I13: =IF((G13<>0),G13-H13," ")
H14: =IF(G14<>0,G14*H$2/(100+H$2)," ") | I14: =IF((G14<>0),G14-H14," ")
H15: =IF(H$4="X"," ",IF(G15<>0,G15*H$2/(100+H$2)," ")) | I15: =IF((G15<>0),G15-H15," ")
H16: =IF(H$4="X"," ",IF(G16<>0,G16*H$2/(100+H$2)," ")) | I16: =IF((G16<>0),G16-H16," ")
H17: =IF(H$4="X"," ",IF(G17<>0,G17*H$2/(100+H$2)," ")) | I17: =IF((G17<>0),G17-H17," ")
H18: =IF(H$4="X"," ",IF(G18<>0,G18*H$2/(100+H$2)," ")) | I18: =IF((G18<>0),G18-H18," ")
H19: =IF(H$4="X"," ",IF(G19<>0,G19*H$2/(100+H$2)," ")) | I19: =IF((G19<>0),G19-H19," ")
H20: =IF(H$4="X"," ",IF(G20<>0,G20*H$2/(100+H$2)," ")) | I20: =IF((G20<>0),G20-H20," ")
H21: =IF(H$4="X"," ",IF(G21<>0,G21*H$2/(100+H$2)," ")) | I21: =IF((G21<>0),G21-H21," ")
H22: =IF(H$4="X"," ",IF(G22<>0,G22*H$2/(100+H$2)," ")) | I22: =IF((G22<>0),G22-H22," ")
H23: =IF(H$4="X"," ",IF(G23<>0,G23*H$2/(100+H$2)," ")) | I23: =IF((G23<>0),G23-H23," ")
H24: =IF(H$4="X"," ",IF(G24<>0,G24*H$2/(100+H$2)," ")) | I24: =IF((G24<>0),G24-H24," ")
H25: =IF(H$4="X"," ",IF(G25<>0,G25*H$2/(100+H$2)," ")) | I25: =IF((G25<>0),G25-H25," ")
H26: =IF(H$4="X"," ",IF(G26<>0,G26*H$2/(100+H$2)," ")) | I26: =IF((G26<>0),G26-H26," ")
... H200: =IF(H$4="X"," ",IF(G200<>0,G200*H$2/(100+H$2)," ")) | I200: =IF((G200<>0),G200-H200," ")
A201: Entries below this row are not included in Row 1 Totals | H201: =NA() -> #N/A

Sheet P03Y1
A1: USE FOR VAT PERIODS OUTSIDE FINANCIAL YEAR | C1: Purchase Invoice Number or Reference | E1: Total for Month | G1: =SUM(G5:G200) -> 0 | H1: =SUM(H5:H200) -> 0 | I1: =SUM(I5:I200) -> 0
A2: Purchase Date | B2: =IF((I1-SUM(P1:AL1)<>0),"COMPLETE EXPENSE ANALYSIS by inserting expense letter in col F","Supplier") -> Supplier | E2: Purchase Description | G2: Total Purchase Value incl Vat | H2: =[3]OpeningCreditors!$H$2 -> 20 | I2: Purchases Net of Vat
H3: Vat Input
H5: =IF(G5<>0,G5*H$2/(100+H$2)," ") | I5: =IF((G5<>0),G5-H5," ")
H6: =IF(G6<>0,G6*H$2/(100+H$2)," ") | I6: =IF((G6<>0),G6-H6," ")
H7: =IF(G7<>0,G7*H$2/(100+H$2)," ") | I7: =IF((G7<>0),G7-H7," ")
H8: =IF(G8<>0,G8*H$2/(100+H$2)," ") | I8: =IF((G8<>0),G8-H8," ")
H9: =IF(G9<>0,G9*H$2/(100+H$2)," ") | I9: =IF((G9<>0),G9-H9," ")
H10: =IF(G10<>0,G10*H$2/(100+H$2)," ") | I10: =IF((G10<>0),G10-H10," ")
H11: =IF(G11<>0,G11*H$2/(100+H$2)," ") | I11: =IF((G11<>0),G11-H11," ")
H12: =IF(G12<>0,G12*H$2/(100+H$2)," ") | I12: =IF((G12<>0),G12-H12," ")
H13: =IF(G13<>0,G13*H$2/(100+H$2)," ") | I13: =IF((G13<>0),G13-H13," ")
H14: =IF(G14<>0,G14*H$2/(100+H$2)," ") | I14: =IF((G14<>0),G14-H14," ")
H15: =IF(H$4="X"," ",IF(G15<>0,G15*H$2/(100+H$2)," ")) | I15: =IF((G15<>0),G15-H15," ")
H16: =IF(H$4="X"," ",IF(G16<>0,G16*H$2/(100+H$2)," ")) | I16: =IF((G16<>0),G16-H16," ")
H17: =IF(H$4="X"," ",IF(G17<>0,G17*H$2/(100+H$2)," ")) | I17: =IF((G17<>0),G17-H17," ")
H18: =IF(H$4="X"," ",IF(G18<>0,G18*H$2/(100+H$2)," ")) | I18: =IF((G18<>0),G18-H18," ")
H19: =IF(H$4="X"," ",IF(G19<>0,G19*H$2/(100+H$2)," ")) | I19: =IF((G19<>0),G19-H19," ")
H20: =IF(H$4="X"," ",IF(G20<>0,G20*H$2/(100+H$2)," ")) | I20: =IF((G20<>0),G20-H20," ")
H21: =IF(H$4="X"," ",IF(G21<>0,G21*H$2/(100+H$2)," ")) | I21: =IF((G21<>0),G21-H21," ")
H22: =IF(H$4="X"," ",IF(G22<>0,G22*H$2/(100+H$2)," ")) | I22: =IF((G22<>0),G22-H22," ")
H23: =IF(H$4="X"," ",IF(G23<>0,G23*H$2/(100+H$2)," ")) | I23: =IF((G23<>0),G23-H23," ")
H24: =IF(H$4="X"," ",IF(G24<>0,G24*H$2/(100+H$2)," ")) | I24: =IF((G24<>0),G24-H24," ")
H25: =IF(H$4="X"," ",IF(G25<>0,G25*H$2/(100+H$2)," ")) | I25: =IF((G25<>0),G25-H25," ")
H26: =IF(H$4="X"," ",IF(G26<>0,G26*H$2/(100+H$2)," ")) | I26: =IF((G26<>0),G26-H26," ")
... H200: =IF(H$4="X"," ",IF(G200<>0,G200*H$2/(100+H$2)," ")) | I200: =IF((G200<>0),G200-H200," ")
A201: Entries below this row are not included in Row 1 Totals | H201: =NA() -> #N/A

Sheet P04Y2
A1: USE FOR VAT PERIODS OUTSIDE FINANCIAL YEAR | C1: Purchase Invoice Number or Reference | E1: Total for Month | G1: =SUM(G5:G200) -> 0 | H1: =SUM(H5:H200) -> 0 | I1: =SUM(I5:I200) -> 0
A2: Purchase Date | B2: =IF((I1-SUM(P1:AL1)<>0),"COMPLETE EXPENSE ANALYSIS by inserting expense letter in col F","Supplier") -> Supplier | E2: Purchase Description | G2: Total Purchase Value incl Vat | H2: =[3]ClosingCreditors!$H$2 -> 20 | I2: Purchases Net of Vat
H3: Vat Input
H5: =IF(G5<>0,G5*H$2/(100+H$2)," ") | I5: =IF((G5<>0),G5-H5," ")
H6: =IF(G6<>0,G6*H$2/(100+H$2)," ") | I6: =IF((G6<>0),G6-H6," ")
H7: =IF(G7<>0,G7*H$2/(100+H$2)," ") | I7: =IF((G7<>0),G7-H7," ")
H8: =IF(G8<>0,G8*H$2/(100+H$2)," ") | I8: =IF((G8<>0),G8-H8," ")
H9: =IF(G9<>0,G9*H$2/(100+H$2)," ") | I9: =IF((G9<>0),G9-H9," ")
H10: =IF(G10<>0,G10*H$2/(100+H$2)," ") | I10: =IF((G10<>0),G10-H10," ")
H11: =IF(G11<>0,G11*H$2/(100+H$2)," ") | I11: =IF((G11<>0),G11-H11," ")
H12: =IF(G12<>0,G12*H$2/(100+H$2)," ") | I12: =IF((G12<>0),G12-H12," ")
H13: =IF(G13<>0,G13*H$2/(100+H$2)," ") | I13: =IF((G13<>0),G13-H13," ")
H14: =IF(G14<>0,G14*H$2/(100+H$2)," ") | I14: =IF((G14<>0),G14-H14," ")
H15: =IF(H$4="X"," ",IF(G15<>0,G15*H$2/(100+H$2)," ")) | I15: =IF((G15<>0),G15-H15," ")
H16: =IF(H$4="X"," ",IF(G16<>0,G16*H$2/(100+H$2)," ")) | I16: =IF((G16<>0),G16-H16," ")
H17: =IF(H$4="X"," ",IF(G17<>0,G17*H$2/(100+H$2)," ")) | I17: =IF((G17<>0),G17-H17," ")
H18: =IF(H$4="X"," ",IF(G18<>0,G18*H$2/(100+H$2)," ")) | I18: =IF((G18<>0),G18-H18," ")
H19: =IF(H$4="X"," ",IF(G19<>0,G19*H$2/(100+H$2)," ")) | I19: =IF((G19<>0),G19-H19," ")
H20: =IF(H$4="X"," ",IF(G20<>0,G20*H$2/(100+H$2)," ")) | I20: =IF((G20<>0),G20-H20," ")
H21: =IF(H$4="X"," ",IF(G21<>0,G21*H$2/(100+H$2)," ")) | I21: =IF((G21<>0),G21-H21," ")
H22: =IF(H$4="X"," ",IF(G22<>0,G22*H$2/(100+H$2)," ")) | I22: =IF((G22<>0),G22-H22," ")
H23: =IF(H$4="X"," ",IF(G23<>0,G23*H$2/(100+H$2)," ")) | I23: =IF((G23<>0),G23-H23," ")
H24: =IF(H$4="X"," ",IF(G24<>0,G24*H$2/(100+H$2)," ")) | I24: =IF((G24<>0),G24-H24," ")
H25: =IF(H$4="X"," ",IF(G25<>0,G25*H$2/(100+H$2)," ")) | I25: =IF((G25<>0),G25-H25," ")
H26: =IF(H$4="X"," ",IF(G26<>0,G26*H$2/(100+H$2)," ")) | I26: =IF((G26<>0),G26-H26," ")
... H200: =IF(H$4="X"," ",IF(G200<>0,G200*H$2/(100+H$2)," ")) | I200: =IF((G200<>0),G200-H200," ")
A201: Entries below this row are not included in Row 1 Totals | H201: =NA() -> #N/A

Sheet P05Y2
A1: USE FOR VAT PERIODS OUTSIDE FINANCIAL YEAR | C1: Purchase Invoice Number or Reference | E1: Total for Month | G1: =SUM(G5:G200) -> 0 | H1: =SUM(H5:H200) -> 0 | I1: =SUM(I5:I200) -> 0
A2: Purchase Date | B2: =IF((I1-SUM(P1:AL1)<>0),"COMPLETE EXPENSE ANALYSIS by inserting expense letter in col F","Supplier") -> Supplier | E2: Purchase Description | G2: Total Purchase Value incl Vat | H2: =[3]ClosingCreditors!$H$2 -> 20 | I2: Purchases Net of Vat
H3: Vat Input
H5: =IF(G5<>0,G5*H$2/(100+H$2)," ") | I5: =IF((G5<>0),G5-H5," ")
H6: =IF(G6<>0,G6*H$2/(100+H$2)," ") | I6: =IF((G6<>0),G6-H6," ")
H7: =IF(G7<>0,G7*H$2/(100+H$2)," ") | I7: =IF((G7<>0),G7-H7," ")
H8: =IF(G8<>0,G8*H$2/(100+H$2)," ") | I8: =IF((G8<>0),G8-H8," ")
H9: =IF(G9<>0,G9*H$2/(100+H$2)," ") | I9: =IF((G9<>0),G9-H9," ")
H10: =IF(G10<>0,G10*H$2/(100+H$2)," ") | I10: =IF((G10<>0),G10-H10," ")
H11: =IF(G11<>0,G11*H$2/(100+H$2)," ") | I11: =IF((G11<>0),G11-H11," ")
H12: =IF(G12<>0,G12*H$2/(100+H$2)," ") | I12: =IF((G12<>0),G12-H12," ")
H13: =IF(G13<>0,G13*H$2/(100+H$2)," ") | I13: =IF((G13<>0),G13-H13," ")
H14: =IF(G14<>0,G14*H$2/(100+H$2)," ") | I14: =IF((G14<>0),G14-H14," ")
H15: =IF(H$4="X"," ",IF(G15<>0,G15*H$2/(100+H$2)," ")) | I15: =IF((G15<>0),G15-H15," ")
H16: =IF(H$4="X"," ",IF(G16<>0,G16*H$2/(100+H$2)," ")) | I16: =IF((G16<>0),G16-H16," ")
H17: =IF(H$4="X"," ",IF(G17<>0,G17*H$2/(100+H$2)," ")) | I17: =IF((G17<>0),G17-H17," ")
H18: =IF(H$4="X"," ",IF(G18<>0,G18*H$2/(100+H$2)," ")) | I18: =IF((G18<>0),G18-H18," ")
H19: =IF(H$4="X"," ",IF(G19<>0,G19*H$2/(100+H$2)," ")) | I19: =IF((G19<>0),G19-H19," ")
H20: =IF(H$4="X"," ",IF(G20<>0,G20*H$2/(100+H$2)," ")) | I20: =IF((G20<>0),G20-H20," ")
H21: =IF(H$4="X"," ",IF(G21<>0,G21*H$2/(100+H$2)," ")) | I21: =IF((G21<>0),G21-H21," ")
H22: =IF(H$4="X"," ",IF(G22<>0,G22*H$2/(100+H$2)," ")) | I22: =IF((G22<>0),G22-H22," ")
H23: =IF(H$4="X"," ",IF(G23<>0,G23*H$2/(100+H$2)," ")) | I23: =IF((G23<>0),G23-H23," ")
H24: =IF(H$4="X"," ",IF(G24<>0,G24*H$2/(100+H$2)," ")) | I24: =IF((G24<>0),G24-H24," ")
H25: =IF(H$4="X"," ",IF(G25<>0,G25*H$2/(100+H$2)," ")) | I25: =IF((G25<>0),G25-H25," ")
H26: =IF(H$4="X"," ",IF(G26<>0,G26*H$2/(100+H$2)," ")) | I26: =IF((G26<>0),G26-H26," ")
... H200: =IF(H$4="X"," ",IF(G200<>0,G200*H$2/(100+H$2)," ")) | I200: =IF((G200<>0),G200-H200," ")
A201: Entries below this row are not included in Row 1 Totals | H201: =NA() -> #N/A
